Workbook
Name ADEmail: Sheet3!$J$4:$J$1536
Name Age: Sheet3!$U$4:$U$1536
Name Age_Group: Sheet3!$V$4:$V$1536
Name BusinessUnit: Sheet3!$K$4:$K$1536
Name Current_Employee_Rating: Sheet3!$AD$4:$AD$1536
Name DepartmentType: Sheet3!$R$4:$R$1536
Name Division: Sheet3!$S$4:$S$1536
Name DOB: Sheet3!$T$4:$T$1536
Name EmpID: Sheet3!$A$4:$A$1536
Name EmployeeClassificationType: Sheet3!$O$4:$O$1536
Name EmployeeStatus: Sheet3!$L$4:$L$1536
Name EmployeeType: Sheet3!$M$4:$M$1536
Name ExitDate: Sheet3!$E$4:$E$1536
Name FirstName: Sheet3!$B$4:$B$1536
Name GenderCode: Sheet3!$Y$4:$Y$1536
Name JobFunctionDescription: Sheet3!$X$4:$X$1536
Name LastName: Sheet3!$C$4:$C$1536
Name LocationCode: Sheet3!$Z$4:$Z$1536
Name MaritalDesc: Sheet3!$AB$4:$AB$1536
Name PayZone: Sheet3!$N$4:$N$1536
Name Performance_Score: Sheet3!$AC$4:$AC$1536
Name RaceDesc: Sheet3!$AA$4:$AA$1536
Name Slicer_GenderCode: #N/A
Name Slicer_GenderCode1: #N/A
Name Slicer_GenderCode2: #N/A
Name StartDate: Sheet3!$D$4:$D$1536
Name State: Sheet3!$W$4:$W$1536
Name Status: Sheet3!$G$4:$G$1536
Name Supervisor: Sheet3!$I$4:$I$1536
Name Tenure: Sheet3!$F$4:$F$1536
Name TerminationDescription: Sheet3!$Q$4:$Q$1536
Name TerminationType: Sheet3!$P$4:$P$1536
Name Title: Sheet3!$H$4:$H$1536

Sheet Sheet1
A3: Count of EmpID
A4: 3000
A6: Row Labels | B6: Count of EmpID2 | C6: Count of EmpID
A7: Active | B7: 0.489 | C7: 1467
A8: Attrition | B8: 0.511 | C8: 1533
A9: Grand Total | B9: 1 | C9: 3000
A11: Average of Age
A12: 54.276056
A14: Row Labels | B14: Count of EmpID | D14: Count of EmpID | E14: Column Labels
A15: Software Engineer | B15: 48 | D15: Row Labels | E15: Female | F15: Male | G15: Grand Total
A16: Production Manager | B16: 84 | D16: 20-29 | E16: 73 | F16: 79 | G16: 152
A17: Area Sales Manager | B17: 149 | D17: 30-39 | E17: 161 | F17: 112 | G17: 273
A18: Production Technician II | B18: 254 | D18: 40-49 | E18: 141 | F18: 99 | G18: 240
A19: Production Technician I | B19: 656 | D19: 50-59 | E19: 124 | F19: 98 | G19: 222
A20: Grand Total | B20: 1191 | D20: 60-69 | E20: 158 | F20: 121 | G20: 279
D21: 70-79 | E21: 141 | F21: 112 | G21: 253
A22: Row Labels | B22: Count of EmpID | D22: 80-89 | E22: 67 | F22: 47 | G22: 114
A23: Hispanic | B23: 292 | D23: Grand Total | E23: 865 | F23: 668 | G23: 1533
A24: Other | B24: 298
A25: White | B25: 299 | D25: Row Labels | E25: Count of EmpID | G25: Row Labels | H25: Count of EmpID
A26: Black | B26: 311 | D26: Executive Office | E26: 19 | G26: Zone A | H26: 536
A27: Asian | B27: 333 | D27: Admin Offices | E27: 48 | G27: Zone B | H27: 519
A28: Grand Total | B28: 1533 | D28: Software Engineering | E28: 64 | G28: Zone C | H28: 478
D29: Sales | E29: 164 | G29: Grand Total | H29: 1533
A30: Row Labels | B30: Count of EmpID | D30: IT/IS | E30: 224
A31: Retirement | B31: 377 | D31: Production | E31: 1014
A32: Resignation | B32: 380 | D32: Grand Total | E32: 1533
A33: Involuntary | B33: 388
A34: Voluntary | B34: 388
A35: Grand Total | B35: 1533
A37: Row Labels | B37: Count of EmpID | D37: Row Labels | E37: Count of EmpID
A38: Contract | B38: 514 | D38: Widowed | E38: 371
A39: Full-Time | B39: 534 | D39: Divorced | E39: 381
A40: Part-Time | B40: 485 | D40: Single | E40: 381
A41: Grand Total | B41: 1533 | D41: Married | E41: 400
D42: Grand Total | E42: 1533

Sheet Executive Overview
AB4: Total Employees | AC4: =GETPIVOTDATA("EmpID",Sheet1!$A$3) -> 3000
AB5: Active Employees | AC5: =GETPIVOTDATA("Count of EmpID",Sheet1!$A$6,"Status","Active") -> 1467 | AD5: =GETPIVOTDATA("Count of EmpID2",Sheet1!$A$6,"Status","Active") -> 0.489
AB6: Attrition | AC6: =GETPIVOTDATA("Count of EmpID",Sheet1!$A$6,"Status","Attrition") -> 1533 | AD6: =GETPIVOTDATA("Count of EmpID2",Sheet1!$A$6,"Status","Attrition") -> 0.511
AB7: Average Age | AC7: =GETPIVOTDATA("Age",Sheet1!$A$11) -> 54.276056

Sheet Department

Sheet Employee

Sheet employee_data(1)
A4: EmpID | B4: FirstName | C4: LastName | D4: StartDate | E4: ExitDate | F4: Tenure | G4: Status | H4: Title | I4: Supervisor | J4: ADEmail | K4: BusinessUnit | L4: EmployeeStatus | M4: EmployeeType | N4: PayZone | O4: EmployeeClassificationType | P4: TerminationType | Q4: TerminationDescription | R4: DepartmentType | S4: Division | T4: DOB | U4: Age | V4: Age Group | W4: State | X4: JobFunctionDescription | Y4: GenderCode | Z4: LocationCode | AA4: RaceDesc | AB4: MaritalDesc | AC4: Performance Score | AD4: Current Employee Rating
A5: 3427 | B5: Uriah | C5: Bridges | D5: 43728 | F5: =IF(Table1[[#This Row],[ExitDate]],QUOTIENT(Table1[[#This Row],[ExitDate]]-Table1[[#This Row],[StartDate]],365/12),"") | G5: =IF(Table1[[#This Row],[ExitDate]], "Attrition", "Active") -> Active | H5: Production Technician I | I5: Peter Oneill | J5: uriah.bridges@bilearner.com | K5: CCDR | L5: Active | M5: Contract | N5: Zone C | O5: Temporary | P5: Unk | R5: Production | S5: Finance & Accounting | T5: 25483 | U5: =YEARFRAC(Table1[[#This Row],[DOB]],TODAY()) -> 56.211111 | V5: {=_xlfn.IFS(Table1[[#This Row],[Age]] < 30, "20-29", Table1[[#This Row],[Age]]<40,"30-39",Table1[[#This Row],[Age]]<50,"40-49",Table1[[#This Row],[Age]]<60,"50-59",Table1[[#This Row],[Age]]<70, "60-69",Table1[[#This Row],[Age]]<80, "70-79",Table1[[#This Row],[Age]]<90,"80-89")} -> 50-59 | W5: MA | X5: Accounting | Y5: Female | Z5: 34904 | AA5: White | AB5: Widowed | AC5: Fully Meets | AD5: 4
A6: 3428 | B6: Paula | C6: Small | D6: 44968 | F6: =IF(Table1[[#This Row],[ExitDate]],QUOTIENT(Table1[[#This Row],[ExitDate]]-Table1[[#This Row],[StartDate]],365/12),"") | G6: =IF(Table1[[#This Row],[ExitDate]], "Attrition", "Active") -> Active | H6: Production Technician I | I6: Renee Mccormick | J6: paula.small@bilearner.com | K6: EW | L6: Active | M6: Contract | N6: Zone A | O6: Part-Time | P6: Unk | R6: Production | S6: Aerial | T6: 23984 | U6: =YEARFRAC(Table1[[#This Row],[DOB]],TODAY()) -> 60.313889 | V6: {=_xlfn.IFS(Table1[[#This Row],[Age]] < 30, "20-29", Table1[[#This Row],[Age]]<40,"30-39",Table1[[#This Row],[Age]]<50,"40-49",Table1[[#This Row],[Age]]<60,"50-59",Table1[[#This Row],[Age]]<70, "60-69",Table1[[#This Row],[Age]]<80, "70-79",Table1[[#This Row],[Age]]<90,"80-89")} -> 60-69 | W6: MA | X6: Labor | Y6: Male | Z6: 6593 | AA6: Hispanic | AB6: Widowed | AC6: Fully Meets | AD6: 3
A7: 3429 | B7: Edward | C7: Buck | D7: 43444 | F7: =IF(Table1[[#This Row],[ExitDate]],QUOTIENT(Table1[[#This Row],[ExitDate]]-Table1[[#This Row],[StartDate]],365/12),"") | G7: =IF(Table1[[#This Row],[ExitDate]], "Attrition", "Active") -> Active | H7: Area Sales Manager | I7: Crystal Walker | J7: edward.buck@bilearner.com | K7: PL | L7: Active | M7: Full-Time | N7: Zone B | O7: Part-Time | P7: Unk | R7: Sales | S7: General - Sga | T7: 33517 | U7: =YEARFRAC(Table1[[#This Row],[DOB]],TODAY()) -> 34.213889 | V7: {=_xlfn.IFS(Table1[[#This Row],[Age]] < 30, "20-29", Table1[[#This Row],[Age]]<40,"30-39",Table1[[#This Row],[Age]]<50,"40-49",Table1[[#This Row],[Age]]<60,"50-59",Table1[[#This Row],[Age]]<70, "60-69",Table1[[#This Row],[Age]]<80, "70-79",Table1[[#This Row],[Age]]<90,"80-89")} -> 30-39 | W7: MA | X7: Assistant | Y7: Male | Z7: 2330 | AA7: Hispanic | AB7: Widowed | AC7: Fully Meets | AD7: 4
A8: 3430 | B8: Michael | C8: Riordan | D8: 44368 | F8: =IF(Table1[[#This Row],[ExitDate]],QUOTIENT(Table1[[#This Row],[ExitDate]]-Table1[[#This Row],[StartDate]],365/12),"") | G8: =IF(Table1[[#This Row],[ExitDate]], "Attrition", "Active") -> Active | H8: Area Sales Manager | I8: Rebekah Wright | J8: michael.riordan@bilearner.com | K8: CCDR | L8: Active | M8: Contract | N8: Zone A | O8: Full-Time | P8: Unk | R8: Sales | S8: Finance & Accounting | T8: 35889 | U8: =YEARFRAC(Table1[[#This Row],[DOB]],TODAY()) -> 27.719444 | V8: {=_xlfn.IFS(Table1[[#This Row],[Age]] < 30, "20-29", Table1[[#This Row],[Age]]<40,"30-39",Table1[[#This Row],[Age]]<50,"40-49",Table1[[#This Row],[Age]]<60,"50-59",Table1[[#This Row],[Age]]<70, "60-69",Table1[[#This Row],[Age]]<80, "70-79",Table1[[#This Row],[Age]]<90,"80-89")} -> 20-29 | W8: ND | X8: Clerk | Y8: Male | Z8: 58782 | AA8: Other | AB8: Single | AC8: Fully Meets | AD8: 2
A9: 3431 | B9: Jasmine | C9: Onque | D9: 43645 | F9: =IF(Table1[[#This Row],[ExitDate]],QUOTIENT(Table1[[#This Row],[ExitDate]]-Table1[[#This Row],[StartDate]],365/12),"") | G9: =IF(Table1[[#This Row],[ExitDate]], "Attrition", "Active") -> Active | H9: Area Sales Manager | I9: Jason Kim | J9: jasmine.onque@bilearner.com | K9: TNS | L9: Active | M9: Contract | N9: Zone A | O9: Temporary | P9: Unk | R9: Sales | S9: General - Con | T9: 25444 | U9: =YEARFRAC(Table1[[#This Row],[DOB]],TODAY()) -> 56.316667 | V9: {=_xlfn.IFS(Table1[[#This Row],[Age]] < 30, "20-29", Table1[[#This Row],[Age]]<40,"30-39",Table1[[#This Row],[Age]]<50,"40-49",Table1[[#This Row],[Age]]<60,"50-59",Table1[[#This Row],[Age]]<70, "60-69",Table1[[#This Row],[Age]]<80, "70-79",Table1[[#This Row],[Age]]<90,"80-89")} -> 50-59 | W9: FL | X9: Laborer | Y9: Female | Z9: 33174 | AA9: Other | AB9: Married | AC9: Fully Meets | AD9: 3
A10: 3432 | B10: Maruk | C10: Fraval | D10: 43847 | F10: =IF(Table1[[#This Row],[ExitDate]],QUOTIENT(Table1[[#This Row],[ExitDate]]-Table1[[#This Row],[StartDate]],365/12),"") | G10: =IF(Table1[[#This Row],[ExitDate]], "Attrition", "Active") -> Active | H10: Area Sales Manager | I10: Sheri Campos | J10: maruk.fraval@bilearner.com | K10: BPC | L10: Active | M10: Contract | N10: Zone B | O10: Full-Time | P10: Unk | R10: Sales | S10: Field Operations | T10: 17991 | U10: =YEARFRAC(Table1[[#This Row],[DOB]],TODAY()) -> 76.722222 | V10: {=_xlfn.IFS(Table1[[#This Row],[Age]] < 30, "20-29", Table1[[#This Row],[Age]]<40,"30-39",Table1[[#This Row],[Age]]<50,"40-49",Table1[[#This Row],[Age]]<60,"50-59",Table1[[#This Row],[Age]]<70, "60-69",Table1[[#This Row],[Age]]<80, "70-79",Table1[[#This Row],[Age]]<90,"80-89")} -> 70-79 | W10: CT | X10: Driver | Y10: Male | Z10: 6050 | AA10: Black | AB10: Married | AC10: Fully Meets | AD10: 3
A11: 3433 | B11: Latia | C11: Costa | D11: 44657 | E11: 45110 | F11: =IF(Table1[[#This Row],[ExitDate]],QUOTIENT(Table1[[#This Row],[ExitDate]]-Table1[[#This Row],[StartDate]],365/12),"") -> 14 | G11: =IF(Table1[[#This Row],[ExitDate]], "Attrition", "Active") -> Attrition | H11: Area Sales Manager | I11: Jacob Braun | J11: latia.costa@bilearner.com | K11: WBL | L11: Active | M11: Full-Time | N11: Zone B | O11: Temporary | P11: Involuntary | Q11: Me see picture nature degree benefit. | R11: Sales | S11: General - Eng | T11: 15523 | U11: =YEARFRAC(Table1[[#This Row],[DOB]],TODAY()) -> 83.477778 | V11: {=_xlfn.IFS(Table1[[#This Row],[Age]] < 30, "20-29", Table1[[#This Row],[Age]]<40,"30-39",Table1[[#This Row],[Age]]<50,"40-49",Table1[[#This Row],[Age]]<60,"50-59",Table1[[#This Row],[Age]]<70, "60-69",Table1[[#This Row],[Age]]<80, "70-79",Table1[[#This Row],[Age]]<90,"80-89")} -> 80-89 | W11: CA | X11: Technician | Y11: Female | Z11: 90007 | AA11: Hispanic | AB11: Divorced | AC11: Exceeds | AD11: 4
A12: 3434 | B12: Sharlene | C12: Terry | D12: 44141 | E12: 44955 | F12: =IF(Table1[[#This Row],[ExitDate]],QUOTIENT(Table1[[#This Row],[ExitDate]]-Table1[[#This Row],[StartDate]],365/12),"") -> 26 | G12: =IF(Table1[[#This Row],[ExitDate]], "Attrition", "Active") -> Attrition | H12: Area Sales Manager | I12: Tracy Marquez | J12: sharlene.terry@bilearner.com | K12: CCDR | L12: Active | M12: Contract | N12: Zone C | O12: Full-Time | P12: Involuntary | Q12: Blue community type skill story. | R12: Sales | S12: Engineers | T12: 20886 | U12: =YEARFRAC(Table1[[#This Row],[DOB]],TODAY()) -> 68.794444 | V12: {=_xlfn.IFS(Table1[[#This Row],[Age]] < 30, "20-29", Table1[[#This Row],[Age]]<40,"30-39",Table1[[#This Row],[Age]]<50,"40-49",Table1[[#This Row],[Age]]<60,"50-59",Table1[[#This Row],[Age]]<70, "60-69",Table1[[#This Row],[Age]]<80, "70-79",Table1[[#This Row],[Age]]<90,"80-89")} -> 60-69 | W12: OR | X12: Engineer | Y12: Female | Z12: 97756 | AA12: White | AB12: Divorced | AC12: Fully Meets | AD12: 2
A13: 3435 | B13: Jac | C13: McKinzie | D13: 43330 | F13: =IF(Table1[[#This Row],[ExitDate]],QUOTIENT(Table1[[#This Row],[ExitDate]]-Table1[[#This Row],[StartDate]],365/12),"") | G13: =IF(Table1[[#This Row],[ExitDate]], "Attrition", "Active") -> Active | H13: Area Sales Manager | I13: Sharon Becker | J13: jac.mckinzie@bilearner.com | K13: NEL | L13: Active | M13: Contract | N13: Zone B | O13: Part-Time | P13: Unk | R13: Sales | S13: Executive | T13: 27164 | U13: =YEARFRAC(Table1[[#This Row],[DOB]],TODAY()) -> 51.605556 | V13: {=_xlfn.IFS(Table1[[#This Row],[Age]] < 30, "20-29", Table1[[#This Row],[Age]]<40,"30-39",Table1[[#This Row],[Age]]<50,"40-49",Table1[[#This Row],[Age]]<60,"50-59",Table1[[#This Row],[Age]]<70, "60-69",Table1[[#This Row],[Age]]<80, "70-79",Table1[[#This Row],[Age]]<90,"80-89")} -> 50-59 | W13: TX | X13: Executive Assistant | Y13: Male | Z13: 78789 | AA13: Black | AB13: Widowed | AC13: Exceeds | AD13: 3
A14: 3436 | B14: Joseph | C14: Martins | D14: 44582 | E14: 45106 | F14: =IF(Table1[[#This Row],[ExitDate]],QUOTIENT(Table1[[#This Row],[ExitDate]]-Table1[[#This Row],[StartDate]],365/12),"") -> 17 | G14: =IF(Table1[[#This Row],[ExitDate]], "Attrition", "Active") -> Attrition | H14: Area Sales Manager | I14: George Jenkins | J14: joseph.martins@bilearner.com | K14: BPC | L14: Active | M14: Part-Time | N14: Zone B | O14: Temporary | P14: Resignation | Q14: Summer personal bag. | R14: Sales | S14: Engineers | T14: 18213 | U14: =YEARFRAC(Table1[[#This Row],[DOB]],TODAY()) -> 76.116667 | V14: {=_xlfn.IFS(Table1[[#This Row],[Age]] < 30, "20-29", Table1[[#This Row],[Age]]<40,"30-39",Table1[[#This Row],[Age]]<50,"40-49",Table1[[#This Row],[Age]]<60,"50-59",Table1[[#This Row],[Age]]<70, "60-69",Table1[[#This Row],[Age]]<80, "70-79",Table1[[#This Row],[Age]]<90,"80-89")} -> 70-79 | W14: TX | X14: Engineer | Y14: Male | Z14: 78207 | AA14: Asian | AB14: Widowed | AC14: Fully Meets | AD14: 5
A15: 3437 | B15: Myriam | C15: Givens | D15: 45142 | F15: =IF(Table1[[#This Row],[ExitDate]],QUOTIENT(Table1[[#This Row],[ExitDate]]-Table1[[#This Row],[StartDate]],365/12),"") | G15: =IF(Table1[[#This Row],[ExitDate]], "Attrition", "Active") -> Active | H15: Area Sales Manager | I15: Troy White | J15: myriam.givens@bilearner.com | K15: SVG | L15: Active | M15: Contract | N15: Zone B | O15: Temporary | P15: Unk | R15: Sales | S15: Field Operations | T15: 23402 | U15: =YEARFRAC(Table1[[#This Row],[DOB]],TODAY()) -> 61.908333 | V15: {=_xlfn.IFS(Table1[[#This Row],[Age]] < 30, "20-29", Table1[[#This Row],[Age]]<40,"30-39",Table1[[#This Row],[Age]]<50,"40-49",Table1[[#This Row],[Age]]<60,"50-59",Table1[[#This Row],[Age]]<70, "60-69",Table1[[#This Row],[Age]]<80, "70-79",Table1[[#This Row],[Age]]<90,"80-89")} -> 60-69 | W15: IN | X15: Technician | Y15: Female | Z15: 46204 | AA15: Other | AB15: Single | AC15: Fully Meets | AD15: 5
A16: 3438 | B16: Dheepa | C16: Nguyen | D16: 43322 | E16: 43773 | F16: =IF(Table1[[#This Row],[ExitDate]],QUOTIENT(Table1[[#This Row],[ExitDate]]-Table1[[#This Row],[StartDate]],365/12),"") -> 14 | G16: =IF(Table1[[#This Row],[ExitDate]], "Attrition", "Active") -> Attrition | H16: Area Sales Manager | I16: Brian Miller | J16: dheepa.nguyen@bilearner.com | K16: MSC | L16: Active | M16: Full-Time | N16: Zone C | O16: Temporary | P16: Retirement | Q16: Alone once than. More condition pay far. | R16: Sales | S16: General - Con | T16: 17629 | U16: =YEARFRAC(Table1[[#This Row],[DOB]],TODAY()) -> 77.713889 | V16: {=_xlfn.IFS(Table1[[#This Row],[Age]] < 30, "20-29", Table1[[#This Row],[Age]]<40,"30-39",Table1[[#This Row],[Age]]<50,"40-49",Table1[[#This Row],[Age]]<60,"50-59",Table1[[#This Row],[Age]]<70, "60-69",Table1[[#This Row],[Age]]<80, "70-79",Table1[[#This Row],[Age]]<90,"80-89")} -> 70-79 | W16: GA | X16: Technician | Y16: Female | Z16: 30428 | AA16: Asian | AB16: Married | AC16: Fully Meets | AD16: 3
A17: 3439 | B17: Bartholemew | C17: Khemmich | D17: 44706 | E17: 44892 | F17: =IF(Table1[[#This Row],[ExitDate]],QUOTIENT(Table1[[#This Row],[ExitDate]]-Table1[[#This Row],[StartDate]],365/12),"") -> 6 | G17: =IF(Table1[[#This Row],[ExitDate]], "Attrition", "Active") -> Attrition | H17: Area Sales Manager | I17: Charles Parks | J17: bartholemew.khemmich@bilearner.com | K17: EW | L17: Active | M17: Full-Time | N17: Zone A | O17: Temporary | P17: Involuntary | Q17: Foot in theory minute recognize test. | R17: Sales | S17: Splicing | T17: 29914 | U17: =YEARFRAC(Table1[[#This Row],[DOB]],TODAY()) -> 44.080556 | V17: {=_xlfn.IFS(Table1[[#This Row],[Age]] < 30, "20-29", Table1[[#This Row],[Age]]<40,"30-39",Table1[[#This Row],[Age]]<50,"40-49",Table1[[#This Row],[Age]]<60,"50-59",Table1[[#This Row],[Age]]<70, "60-69",Table1[[#This Row],[Age]]<80, "70-79",Table1[[#This Row],[Age]]<90,"80-89")} -> 40-49 | W17: CO | X17: Splicer | Y17: Male | Z17: 80820 | AA17: Other | AB17: Single | AC17: Fully Meets | AD17: 3
A18: 3440 | B18: Xana | C18: Potts | D18: 43804 | E18: 44974 | F18: =IF(Table1[[#This Row],[ExitDate]],QUOTIENT(Table1[[#This Row],[ExitDate]]-Table1[[#This Row],[StartDate]],365/12),"") -> 38 | G18: =IF(Table1[[#This Row],[ExitDate]], "Attrition", "Active") -> Attrition | H18: Area Sales Manager | I18: Gregory Walker | J18: xana.potts@bilearner.com | K18: CCDR | L18: Active | M18: Contract | N18: Zone A | O18: Full-Time | P18: Resignation | Q18: Degree wish science when thing week old. | R18: Sales | S18: Finance & Accounting | T18: 18938 | U18: =YEARFRAC(Table1[[#This Row],[DOB]],TODAY()) -> 74.130556 | V18: {=_xlfn.IFS(Table1[[#This Row],[Age]] < 30, "20-29", Table1[[#This Row],[Age]]<40,"30-39",Table1[[#This Row],[Age]]<50,"40-49",Table1[[#This Row],[Age]]<60,"50-59",Table1[[#This Row],[Age]]<70, "60-69",Table1[[#This Row],[Age]]<80, "70-79",Table1[[#This Row],[Age]]<90,"80-89")} -> 70-79 | W18: KY | X18: Controller | Y18: Female | Z18: 40220 | AA18: White | AB18: Divorced | AC18: Fully Meets | AD18: 3
A19: 3441 | B19: Prater | C19: Jeremy | D19: 43583 | F19: =IF(Table1[[#This Row],[ExitDate]],QUOTIENT(Table1[[#This Row],[ExitDate]]-Table1[[#This Row],[StartDate]],365/12),"") | G19: =IF(Table1[[#This Row],[ExitDate]], "Attrition", "Active") -> Active | H19: Area Sales Manager | I19: Tyler Lewis | J19: prater.jeremy@bilearner.com | K19: BPC | L19: Active | M19: Part-Time | N19: Zone A | O19: Part-Time | P19: Unk | R19: Sales | S19: General - Con | T19: 32833 | U19: =YEARFRAC(Table1[[#This Row],[DOB]],TODAY()) -> 36.088889 | V19: {=_xlfn.IFS(Table1[[#This Row],[Age]] < 30, "20-29", Table1[[#This Row],[Age]]<40,"30-39",Table1[[#This Row],[Age]]<50,"40-49",Table1[[#This Row],[Age]]<60,"50-59",Table1[[#This Row],[Age]]<70, "60-69",Table1[[#This Row],[Age]]<80, "70-79",Table1[[#This Row],[Age]]<90,"80-89")} -> 30-39 | W19: NV | X19: Lineman | Y19: Male | Z19: 89139 | AA19: Asian | AB19: Widowed | AC19: Exceeds | AD19: 4
A20: 3442 | B20: Kaylah | C20: Moon | D20: 43655 | E20: 44728 | F20: =IF(Table1[[#This Row],[ExitDate]],QUOTIENT(Table1[[#This Row],[ExitDate]]-Table1[[#This Row],[StartDate]],365/12),"") -> 35 | G20: =IF(Table1[[#This Row],[ExitDate]], "Attrition", "Active") -> Attrition | H20: Area Sales Manager | I20: Ashley Scott | J20: kaylah.moon@bilearner.com | K20: PYZ | L20: Active | M20: Full-Time | N20: Zone A | O20: Full-Time | P20: Retirement | Q20: Fear particular method stage. | R20: IT/IS | S20: Field Operations | T20: 19322 | U20: =YEARFRAC(Table1[[#This Row],[DOB]],TODAY()) -> 73.080556 | V20: {=_xlfn.IFS(Table1[[#This Row],[Age]] < 30, "20-29", Table1[[#This Row],[Age]]<40,"30-39",Table1[[#This Row],[Age]]<50,"40-49",Table1[[#This Row],[Age]]<60,"50-59",Table1[[#This Row],[Age]]<70, "60-69",Table1[[#This Row],[Age]]<80, "70-79",Table1[[#This Row],[Age]]<90,"80-89")} -> 70-79 | W20: MA | X20: Laborer | Y20: Male | Z20: 2810 | AA20: Black | AB20: Single | AC20: Exceeds | AD20: 2
A21: 3443 | B21: Kristen | C21: Tate | D21: 44291 | E21: 45058 | F21: =IF(Table1[[#This Row],[ExitDate]],QUOTIENT(Table1[[#This Row],[ExitDate]]-Table1[[#This Row],[StartDate]],365/12),"") -> 25 | G21: =IF(Table1[[#This Row],[ExitDate]], "Attrition", "Active") -> Attrition | H21: Area Sales Manager | I21: Lauren Jones | J21: kristen.tate@bilearner.com | K21: WBL | L21: Active | M21: Full-Time | N21: Zone C | O21: Part-Time | P21: Voluntary | Q21: Wall body wonder successful. | R21: IT/IS | S21: Project Management - Con | T21: 34432 | U21: =YEARFRAC(Table1[[#This Row],[DOB]],TODAY()) -> 31.708333 | V21: {=_xlfn.IFS(Table1[[#This Row],[Age]] < 30, "20-29", Table1[[#This Row],[Age]]<40,"30-39",Table1[[#This Row],[Age]]<50,"40-49",Table1[[#This Row],[Age]]<60,"50-59",Table1[[#This Row],[Age]]<70, "60-69",Table1[[#This Row],[Age]]<80, "70-79",Table1[[#This Row],[Age]]<90,"80-89")} -> 30-39 | W21: KY | X21: Coordinator | Y21: Male | Z21: 2621 | AA21: Asian | AB21: Widowed | AC21: Fully Meets | AD21: 3
A22: 3444 | B22: Bobby | C22: Rodgers | D22: 44528 | E22: 44596 | F22: =IF(Table1[[#This Row],[ExitDate]],QUOTIENT(Table1[[#This Row],[ExitDate]]-Table1[[#This Row],[StartDate]],365/12),"") -> 2 | G22: =IF(Table1[[#This Row],[ExitDate]], "Attrition", "Active") -> Attrition | H22: Area Sales Manager | I22: Matthew Jackson | J22: bobby.rodgers@bilearner.com | K22: NEL | L22: Active | M22: Contract | N22: Zone A | O22: Part-Time | P22: Voluntary | Q22: Visit foot nearly radio treatment. | R22: Sales | S22: Engineers | T22: 30635 | U22: =YEARFRAC(Table1[[#This Row],[DOB]],TODAY()) -> 42.105556 | V22: {=_xlfn.IFS(Table1[[#This Row],[Age]] < 30, "20-29", Table1[[#This Row],[Age]]<40,"30-39",Table1[[#This Row],[Age]]<50,"40-49",Table1[[#This Row],[Age]]<60,"50-59",Table1[[#This Row],[Age]]<70, "60-69",Table1[[#This Row],[Age]]<80, "70-79",Table1[[#This Row],[Age]]<90,"80-89")} -> 40-49 | W22: KY | X22: Director | Y22: Male | Z22: 44553 | AA22: Other | AB22: Widowed | AC22: Fully Meets | AD22: 3
A23: 3445 | B23: Reid | C23: Park | D23: 44212 | F23: =IF(Table1[[#This Row],[ExitDate]],QUOTIENT(Table1[[#This Row],[ExitDate]]-Table1[[#This Row],[StartDate]],365/12),"") | G23: =IF(Table1[[#This Row],[ExitDate]], "Attrition", "Active") -> Active | H23: Area Sales Manager | I23: Michelle Mitchell | J23: reid.park@bilearner.com | K23: PL | L23: Active | M23: Contract | N23: Zone C | O23: Full-Time | P23: Unk | R23: Sales | S23: Project Management - Con | T23: 31388 | U23: =YEARFRAC(Table1[[#This Row],[DOB]],TODAY()) -> 40.044444 | V23: {=_xlfn.IFS(Table1[[#This Row],[Age]] < 30, "20-29", Table1[[#This Row],[Age]]<40,"30-39",Table1[[#This Row],[Age]]<50,"40-49",Table1[[#This Row],[Age]]<60,"50-59",Table1[[#This Row],[Age]]<70, "60-69",Table1[[#This Row],[Age]]<80, "70-79",Table1[[#This Row],[Age]]<90,"80-89")} -> 40-49 | W23: KY | X23: Supervisor | Y23: Female | Z23: 5360 | AA23: Other | AB23: Married | AC23: Exceeds | AD23: 4
A24: 3446 | B24: Hector | C24: Dalton | D24: 44432 | F24: =IF(Table1[[#This Row],[ExitDate]],QUOTIENT(Table1[[#This Row],[ExitDate]]-Table1[[#This Row],[StartDate]],365/12),"") | G24: =IF(Table1[[#This Row],[ExitDate]], "Attrition", "Active") -> Active | H24: Area Sales Manager | I24: Sydney French | J24: hector.dalton@bilearner.com | K24: BPC | L24: Active | M24: Part-Time | N24: Zone A | O24: Part-Time | P24: Unk | R24: Sales | S24: Field Operations | T24: 35186 | U24: =YEARFRAC(Table1[[#This Row],[DOB]],TODAY()) -> 29.644444 | V24: {=_xlfn.IFS(Table1[[#This Row],[Age]] < 30, "20-29", Table1[[#This Row],[Age]]<40,"30-39",Table1[[#This Row],[Age]]<50,"40-49",Table1[[#This Row],[Age]]<60,"50-59",Table1[[#This Row],[Age]]<70, "60-69",Table1[[#This Row],[Age]]<80, "70-79",Table1[[#This Row],[Age]]<90,"80-89")} -> 20-29 | W24: TX | X24: Driller | Y24: Female | Z24: 16325 | AA24: White | AB24: Divorced | AC24: Exceeds | AD24: 2
A25: 3447 | B25: Mariela | C25: Schultz | D25: 43977 | E25: 45095 | F25: =IF(Table1[[#This Row],[ExitDate]],QUOTIENT(Table1[[#This Row],[ExitDate]]-Table1[[#This Row],[StartDate]],365/12),"") -> 36 | G25: =IF(Table1[[#This Row],[ExitDate]], "Attrition", "Active") -> Attrition | H25: Area Sales Manager | I25: Michelle Evans MD | J25: mariela.schultz@bilearner.com | K25: CCDR | L25: Future Start | M25: Part-Time | N25: Zone C | O25: Part-Time | P25: Involuntary | Q25: Unit pass office southern break one. | R25: Sales | S25: General - Con | T25: 23424 | U25: =YEARFRAC(Table1[[#This Row],[DOB]],TODAY()) -> 61.85 | V25: {=_xlfn.IFS(Table1[[#This Row],[Age]] < 30, "20-29", Table1[[#This Row],[Age]]<40,"30-39",Table1[[#This Row],[Age]]<50,"40-49",Table1[[#This Row],[Age]]<60,"50-59",Table1[[#This Row],[Age]]<70, "60-69",Table1[[#This Row],[Age]]<80, "70-79",Table1[[#This Row],[Age]]<90,"80-89")} -> 60-69 | W25: TX | X25: Technician | Y25: Female | Z25: 43481 | AA25: Asian | AB25: Widowed | AC25: Fully Meets | AD25: 3
A26: 3448 | B26: Angela | C26: Molina | D26: 43739 | E26: 44141 | F26: =IF(Table1[[#This Row],[ExitDate]],QUOTIENT(Table1[[#This Row],[ExitDate]]-Table1[[#This Row],[StartDate]],365/12),"") -> 13 | G26: =IF(Table1[[#This Row],[ExitDate]], "Attrition", "Active") -> Attrition | H26: Area Sales Manager | I26: Patricia Cook | J26: angela.molina@bilearner.com | K26: SVG | L26: Future Start | M26: Full-Time | N26: Zone A | O26: Temporary | P26: Retirement | Q26: List class mind. | R26: Sales | S26: Engineers | T26: 21317 | U26: =YEARFRAC(Table1[[#This Row],[DOB]],TODAY()) -> 67.613889 | V26: {=_xlfn.IFS(Table1[[#This Row],[Age]] < 30, "20-29", Table1[[#This Row],[Age]]<40,"30-39",Table1[[#This Row],[Age]]<50,"40-49",Table1[[#This Row],[Age]]<60,"50-59",Table1[[#This Row],[Age]]<70, "60-69",Table1[[#This Row],[Age]]<80, "70-79",Table1[[#This Row],[Age]]<90,"80-89")} -> 60-69 | W26: TX | X26: Specialist | Y26: Male | Z26: 50705 | AA26: Asian | AB26: Widowed | AC26: Fully Meets | AD26: 3
A27: 3449 | B27: Gerald | C27: Preston | D27: 45056 | E27: 45073 | F27: =IF(Table1[[#This Row],[ExitDate]],QUOTIENT(Table1[[#This Row],[ExitDate]]-Table1[[#This Row],[StartDate]],365/12),"") -> 0 | G27: =IF(Table1[[#This Row],[ExitDate]], "Attrition", "Active") -> Attrition | H27: Area Sales Manager | I27: Ashley Reeves | J27: gerald.preston@bilearner.com | K27: EW | L27: Future Start | M27: Contract | N27: Zone B | O27: Temporary | P27: Involuntary | Q27: Price third parent evening. | R27: Sales | S27: General - Eng | T27: 33865 | U27: =YEARFRAC(Table1[[#This Row],[DOB]],TODAY()) -> 33.263889 | V27: {=_xlfn.IFS(Table1[[#This Row],[Age]] < 30, "20-29", Table1[[#This Row],[Age]]<40,"30-39",Table1[[#This Row],[Age]]<50,"40-49",Table1[[#This Row],[Age]]<60,"50-59",Table1[[#This Row],[Age]]<70, "60-69",Table1[[#This Row],[Age]]<80, "70-79",Table1[[#This Row],[Age]]<90,"80-89")} -> 30-39 | W27: CO | X27: Technician | Y27: Male | Z27: 5168 | AA27: Black | AB27: Single | AC27: Fully Meets | AD27: 5
A28: 3450 | B28: Reilly | C28: Moyer | D28: 44075 | E28: 44899 | F28: =IF(Table1[[#This Row],[ExitDate]],QUOTIENT(Table1[[#This Row],[ExitDate]]-Table1[[#This Row],[StartDate]],365/12),"") -> 27 | G28: =IF(Table1[[#This Row],[ExitDate]], "Attrition", "Active") -> Attrition | H28: Area Sales Manager | I28: Stanley Harvey | J28: reilly.moyer@bilearner.com | K28: MSC | L28: Active | M28: Contract | N28: Zone C | O28: Temporary | P28: Resignation | Q28: Cause military a sense. Doctor property may. | R28: Sales | S28: Field Operations | T28: 34557 | U28: =YEARFRAC(Table1[[#This Row],[DOB]],TODAY()) -> 31.366667 | V28: {=_xlfn.IFS(Table1[[#This Row],[Age]] < 30, "20-29", Table1[[#This Row],[Age]]<40,"30-39",Table1[[#This Row],[Age]]<50,"40-49",Table1[[#This Row],[Age]]<60,"50-59",Table1[[#This Row],[Age]]<70, "60-69",Table1[[#This Row],[Age]]<80, "70-79",Table1[[#This Row],[Age]]<90,"80-89")} -> 30-39 | W28: CO | X28: Operator | Y28: Male | Z28: 11765 | AA28: Other | AB28: Single | AC28: Exceeds | AD28: 2
A29: 3451 | B29: Carlee | C29: French | D29: 44245 | E29: 44876 | F29: =IF(Table1[[#This Row],[ExitDate]],QUOTIENT(Table1[[#This Row],[ExitDate]]-Table1[[#This Row],[StartDate]],365/12),"") -> 20 | G29: =IF(Table1[[#This Row],[ExitDate]], "Attrition", "Active") -> Attrition | H29: Area Sales Manager | I29: Michael Bradshaw | J29: carlee.french@bilearner.com | K29: TNS | L29: Active | M29: Contract | N29: Zone C | O29: Full-Time | P29: Voluntary | Q29: Station another son positive. | R29: Sales | S29: General - Con | T29: 24852 | U29: =YEARFRAC(Table1[[#This Row],[DOB]],TODAY()) -> 57.938889 | V29: {=_xlfn.IFS(Table1[[#This Row],[Age]] < 30, "20-29", Table1[[#This Row],[Age]]<40,"30-39",Table1[[#This Row],[Age]]<50,"40-49",Table1[[#This Row],[Age]]<60,"50-59",Table1[[#This Row],[Age]]<70, "60-69",Table1[[#This Row],[Age]]<80, "70-79",Table1[[#This Row],[Age]]<90,"80-89")} -> 50-59 | W29: CO | X29: Technician | Y29: Male | Z29: 71071 | AA29: Other | AB29: Divorced | AC29: Exceeds | AD29: 3
A30: 3452 | B30: Jaydon | C30: Blackburn | D30: 44873 | F30: =IF(Table1[[#This Row],[ExitDate]],QUOTIENT(Table1[[#This Row],[ExitDate]]-Table1[[#This Row],[StartDate]],365/12),"") | G30: =IF(Table1[[#This Row],[ExitDate]], "Attrition", "Active") -> Active | H30: Area Sales Manager | I30: Debbie Crosby | J30: jaydon.blackburn@bilearner.com | K30: PYZ | L30: Active | M30: Part-Time | N30: Zone A | O30: Part-Time | P30: Unk | R30: Sales | S30: General - Con | T30: 17174 | U30: =YEARFRAC(Table1[[#This Row],[DOB]],TODAY()) -> 78.961111 | V30: {=_xlfn.IFS(Table1[[#This Row],[Age]] < 30, "20-29", Table1[[#This Row],[Age]]<40,"30-39",Table1[[#This Row],[Age]]<50,"40-49",Table1[[#This Row],[Age]]<60,"50-59",Table1[[#This Row],[Age]]<70, "60-69",Table1[[#This Row],[Age]]<80, "70-79",Table1[[#This Row],[Age]]<90,"80-89")} -> 70-79 | W30: IN | X30: Foreman | Y30: Male | Z30: 12122 | AA30: Black | AB30: Divorced | AC30: Fully Meets | AD30: 2
A31: 3453 | B31: Bridger | C31: Carter | D31: 44847 | F31: =IF(Table1[[#This Row],[ExitDate]],QUOTIENT(Table1[[#This Row],[ExitDate]]-Table1[[#This Row],[StartDate]],365/12),"") | G31: =IF(Table1[[#This Row],[ExitDate]], "Attrition", "Active") -> Active | H31: Area Sales Manager | I31: Elizabeth Taylor | J31: bridger.carter@bilearner.com | K31: WBL | L31: Active | M31: Contract | N31: Zone C | O31: Part-Time | P31: Unk | R31: Sales | S31: Fielders | T31: 30048 | U31: =YEARFRAC(Table1[[#This Row],[DOB]],TODAY()) -> 43.711111 | V31: {=_xlfn.IFS(Table1[[#This Row],[Age]] < 30, "20-29", Table1[[#This Row],[Age]]<40,"30-39",Table1[[#This Row],[Age]]<50,"40-49",Table1[[#This Row],[Age]]<60,"50-59",Table1[[#This Row],[Age]]<70, "60-69",Table1[[#This Row],[Age]]<80, "70-79",Table1[[#This Row],[Age]]<90,"80-89")} -> 40-49 | W31: MA | X31: Engineer | Y31: Male | Z31: 87065 | AA31: White | AB31: Widowed | AC31: Fully Meets | AD31: 4
A32: 3454 | B32: Leon | C32: Beard | D32: 44815 | F32: =IF(Table1[[#This Row],[ExitDate]],QUOTIENT(Table1[[#This Row],[ExitDate]]-Table1[[#This Row],[StartDate]],365/12),"") | G32: =IF(Table1[[#This Row],[ExitDate]], "Attrition", "Active") -> Active | H32: Area Sales Manager | I32: Brian Dunlap | J32: leon.beard@bilearner.com | K32: PYZ | L32: Active | M32: Full-Time | N32: Zone C | O32: Full-Time | P32: Unk | R32: IT/IS | S32: General - Con | T32: 25597 | U32: =YEARFRAC(Table1[[#This Row],[DOB]],TODAY()) -> 55.9 | V32: {=_xlfn.IFS(Table1[[#This Row],[Age]] < 30, "20-29", Table1[[#This Row],[Age]]<40,"30-39",Table1[[#This Row],[Age]]<50,"40-49",Table1[[#This Row],[Age]]<60,"50-59",Table1[[#This Row],[Age]]<70, "60-69",Table1[[#This Row],[Age]]<80, "70-79",Table1[[#This Row],[Age]]<90,"80-89")} -> 50-59 | W32: KY | X32: Foreman | Y32: Male | Z32: 10415 | AA32: Hispanic | AB32: Married | AC32: Needs Improvement | AD32: 4
A33: 3455 | B33: Charity | C33: Miranda | D33: 44376 | E33: 44747 | F33: =IF(Table1[[#This Row],[ExitDate]],QUOTIENT(Table1[[#This Row],[ExitDate]]-Table1[[#This Row],[StartDate]],365/12),"") -> 12 | G33: =IF(Table1[[#This Row],[ExitDate]], "Attrition", "Active") -> Attrition | H33: Area Sales Manager | I33: Daniel Rodriguez | J33: charity.miranda@bilearner.com | K33: WBL | L33: Active | M33: Full-Time | N33: Zone C | O33: Temporary | P33: Resignation | Q33: Pm local take example fund. Small heavy listen. | R33: Sales | S33: Project Management - Eng | T33: 36178 | U33: =YEARFRAC(Table1[[#This Row],[DOB]],TODAY()) -> 26.930556 | V33: {=_xlfn.IFS(Table1[[#This Row],[Age]] < 30, "20-29", Table1[[#This Row],[Age]]<40,"30-39",Table1[[#This Row],[Age]]<50,"40-49",Table1[[#This Row],[Age]]<60,"50-59",Table1[[#This Row],[Age]]<70, "60-69",Table1[[#This Row],[Age]]<80, "70-79",Table1[[#This Row],[Age]]<90,"80-89")} -> 20-29 | W33: KY | X33: Manager | Y33: Male | Z33: 3763 | AA33: Other | AB33: Widowed | AC33: Exceeds | AD33: 4
A34: 3456 | B34: Axel | C34: Howe | D34: 44991 | F34: =IF(Table1[[#This Row],[ExitDate]],QUOTIENT(Table1[[#This Row],[ExitDate]]-Table1[[#This Row],[StartDate]],365/12),"") | G34: =IF(Table1[[#This Row],[ExitDate]], "Attrition", "Active") -> Active | H34: Area Sales Manager | I34: Martin Hammond | J34: axel.howe@bilearner.com | K34: NEL | L34: Active | M34: Full-Time | N34: Zone A | O34: Temporary | P34: Unk | R34: Sales | S34: Field Operations | T34: 17070 | U34: =YEARFRAC(Table1[[#This Row],[DOB]],TODAY()) -> 79.244444 | V34: {=_xlfn.IFS(Table1[[#This Row],[Age]] < 30, "20-29", Table1[[#This Row],[Age]]<40,"30-39",Table1[[#This Row],[Age]]<50,"40-49",Table1[[#This Row],[Age]]<60,"50-59",Table1[[#This Row],[Age]]<70, "60-69",Table1[[#This Row],[Age]]<80, "70-79",Table1[[#This Row],[Age]]<90,"80-89")} -> 70-79 | W34: KY | X34: Technician | Y34: Female | Z34: 79623 | AA34: Black | AB34: Divorced | AC34: Fully Meets | AD34: 3
A35: 3457 | B35: Milton | C35: Wall | D35: 44099 | F35: =IF(Table1[[#This Row],[ExitDate]],QUOTIENT(Table1[[#This Row],[ExitDate]]-Table1[[#This Row],[StartDate]],365/12),"") | G35: =IF(Table1[[#This Row],[ExitDate]], "Attrition", "Active") -> Active | H35: Area Sales Manager | I35: Sara Bell | J35: milton.wall@bilearner.com | K35: PL | L35: Active | M35: Full-Time | N35: Zone B | O35: Temporary | P35: Unk | R35: Sales | S35: Engineers | T35: 17402 | U35: =YEARFRAC(Table1[[#This Row],[DOB]],TODAY()) -> 78.333333 | V35: {=_xlfn.IFS(Table1[[#This Row],[Age]] < 30, "20-29", Table1[[#This Row],[Age]]<40,"30-39",Table1[[#This Row],[Age]]<50,"40-49",Table1[[#This Row],[Age]]<60,"50-59",Table1[[#This Row],[Age]]<70, "60-69",Table1[[#This Row],[Age]]<80, "70-79",Table1[[#This Row],[Age]]<90,"80-89")} -> 70-79 | W35: KY | X35: Technician | Y35: Female | Z35: 69189 | AA35: White | AB35: Divorced | AC35: Needs Improvement | AD35: 3
A36: 3458 | B36: Cory | C36: Robinson | D36: 44679 | E36: 45070 | F36: =IF(Table1[[#This Row],[ExitDate]],QUOTIENT(Table1[[#This Row],[ExitDate]]-Table1[[#This Row],[StartDate]],365/12),"") -> 12 | G36: =IF(Table1[[#This Row],[ExitDate]], "Attrition", "Active") -> Attrition | H36: Area Sales Manager | I36: Elizabeth Anderson | J36: cory.robinson@bilearner.com | K36: BPC | L36: Future Start | M36: Contract | N36: Zone A | O36: Full-Time | P36: Voluntary | Q36: Several young whether that expert. | R36: Sales | S36: Field Operations | T36: 35289 | U36: =YEARFRAC(Table1[[#This Row],[DOB]],TODAY()) -> 29.363889 | V36: {=_xlfn.IFS(Table1[[#This Row],[Age]] < 30, "20-29", Table1[[#This Row],[Age]]<40,"30-39",Table1[[#This Row],[Age]]<50,"40-49",Table1[[#This Row],[Age]]<60,"50-59",Table1[[#This Row],[Age]]<70, "60-69",Table1[[#This Row],[Age]]<80, "70-79",Table1[[#This Row],[Age]]<90,"80-89")} -> 20-29 | W36: TX | X36: Laborer | Y36: Female | Z36: 5194 | AA36: Hispanic | AB36: Single | AC36: Needs Improvement | AD36: 3
A37: 3459 | B37: Saniya | C37: Yu | D37: 44304 | E37: 44733 | F37: =IF(Table1[[#This Row],[ExitDate]],QUOTIENT(Table1[[#This Row],[ExitDate]]-Table1[[#This Row],[StartDate]],365/12),"") -> 14 | G37: =IF(Table1[[#This Row],[ExitDate]], "Attrition", "Active") -> Attrition | H37: Area Sales Manager | I37: Erin Bailey | J37: saniya.yu@bilearner.com | K37: CCDR | L37: Future Start | M37: Part-Time | N37: Zone A | O37: Full-Time | P37: Retirement | Q37: Science end approach democratic treatment. | R37: Sales | S37: General - Con | T37: 16111 | U37: =YEARFRAC(Table1[[#This Row],[DOB]],TODAY()) -> 81.872222 | V37: {=_xlfn.IFS(Table1[[#This Row],[Age]] < 30, "20-29", Table1[[#This Row],[Age]]<40,"30-39",Table1[[#This Row],[Age]]<50,"40-49",Table1[[#This Row],[Age]]<60,"50-59",Table1[[#This Row],[Age]]<70, "60-69",Table1[[#This Row],[Age]]<80, "70-79",Table1[[#This Row],[Age]]<90,"80-89")} -> 80-89 | W37: TX | X37: Splicer | Y37: Male | Z37: 8779 | AA37: Black | AB37: Widowed | AC37: Exceeds | AD37: 2
A38: 3460 | B38: Alisa | C38: James | D38: 43880 | F38: =IF(Table1[[#This Row],[ExitDate]],QUOTIENT(Table1[[#This Row],[ExitDate]]-Table1[[#This Row],[StartDate]],365/12),"") | G38: =IF(Table1[[#This Row],[ExitDate]], "Attrition", "Active") -> Active | H38: Area Sales Manager | I38: Dennis Henderson | J38: alisa.james@bilearner.com | K38: SVG | L38: Active | M38: Full-Time | N38: Zone A | O38: Full-Time | P38: Unk | R38: Sales | S38: Aerial | T38: 16112 | U38: =YEARFRAC(Table1[[#This Row],[DOB]],TODAY()) -> 81.869444 | V38: {=_xlfn.IFS(Table1[[#This Row],[Age]] < 30, "20-29", Table1[[#This Row],[Age]]<40,"30-39",Table1[[#This Row],[Age]]<50,"40-49",Table1[[#This Row],[Age]]<60,"50-59",Table1[[#This Row],[Age]]<70, "60-69",Table1[[#This Row],[Age]]<80, "70-79",Table1[[#This Row],[Age]]<90,"80-89")} -> 80-89 | W38: TX | X38: Lineman | Y38: Male | Z38: 74682 | AA38: Asian | AB38: Married | AC38: Fully Meets | AD38: 3
A39: 3461 | B39: Lincoln | C39: Compton | D39: 43664 | E39: 44470 | F39: =IF(Table1[[#This Row],[ExitDate]],QUOTIENT(Table1[[#This Row],[ExitDate]]-Table1[[#This Row],[StartDate]],365/12),"") -> 26 | G39: =IF(Table1[[#This Row],[ExitDate]], "Attrition", "Active") -> Attrition | H39: Area Sales Manager | I39: Tammy Conner | J39: lincoln.compton@bilearner.com | K39: EW | L39: Future Start | M39: Full-Time | N39: Zone C | O39: Part-Time | P39: Resignation | Q39: Base scene central unit per argue. Might last of. | R39: Sales | S39: General - Con | T39: 35793 | U39: =YEARFRAC(Table1[[#This Row],[DOB]],TODAY()) -> 27.983333 | V39: {=_xlfn.IFS(Table1[[#This Row],[Age]] < 30, "20-29", Table1[[#This Row],[Age]]<40,"30-39",Table1[[#This Row],[Age]]<50,"40-49",Table1[[#This Row],[Age]]<60,"50-59",Table1[[#This Row],[Age]]<70, "60-69",Table1[[#This Row],[Age]]<80, "70-79",Table1[[#This Row],[Age]]<90,"80-89")} -> 20-29 | W39: CO | X39: Foreman | Y39: Male | Z39: 78046 | AA39: Hispanic | AB39: Married | AC39: Needs Improvement | AD39: 1
A40: 3462 | B40: Aliana | C40: Nolan | D40: 43356 | E40: 44456 | F40: =IF(Table1[[#This Row],[ExitDate]],QUOTIENT(Table1[[#This Row],[ExitDate]]-Table1[[#This Row],[StartDate]],365/12),"") -> 36 | G40: =IF(Table1[[#This Row],[ExitDate]], "Attrition", "Active") -> Attrition | H40: Area Sales Manager | I40: Brianna Mathews | J40: aliana.nolan@bilearner.com | K40: MSC | L40: Active | M40: Contract | N40: Zone A | O40: Full-Time | P40: Involuntary | Q40: Yourself book budget product. | R40: Sales | S40: Field Operations | T40: 15562 | U40: =YEARFRAC(Table1[[#This Row],[DOB]],TODAY()) -> 83.372222 | V40: {=_xlfn.IFS(Table1[[#This Row],[Age]] < 30, "20-29", Table1[[#This Row],[Age]]<40,"30-39",Table1[[#This Row],[Age]]<50,"40-49",Table1[[#This Row],[Age]]<60,"50-59",Table1[[#This Row],[Age]]<70, "60-69",Table1[[#This Row],[Age]]<80, "70-79",Table1[[#This Row],[Age]]<90,"80-89")} -> 80-89 | W40: CO | X40: Coordinator | Y40: Male | Z40: 27270 | AA40: Hispanic | AB40: Divorced | AC40: Needs Improvement | AD40: 3
A41: 3463 | B41: Kayden | C41: Dodson | D41: 43951 | E41: 44395 | F41: =IF(Table1[[#This Row],[ExitDate]],QUOTIENT(Table1[[#This Row],[ExitDate]]-Table1[[#This Row],[StartDate]],365/12),"") -> 14 | G41: =IF(Table1[[#This Row],[ExitDate]], "Attrition", "Active") -> Attrition | H41: Area Sales Manager | I41: Jessica Peters | J41: kayden.dodson@bilearner.com | K41: TNS | L41: Active | M41: Part-Time | N41: Zone A | O41: Temporary | P41: Retirement | Q41: Paper can score else investment. | R41: Sales | S41: Field Operations | T41: 18800 | U41: =YEARFRAC(Table1[[#This Row],[DOB]],TODAY()) -> 74.505556 | V41: {=_xlfn.IFS(Table1[[#This Row],[Age]] < 30, "20-29", Table1[[#This Row],[Age]]<40,"30-39",Table1[[#This Row],[Age]]<50,"40-49",Table1[[#This Row],[Age]]<60,"50-59",Table1[[#This Row],[Age]]<70, "60-69",Table1[[#This Row],[Age]]<80, "70-79",Table1[[#This Row],[Age]]<90,"80-89")} -> 70-79 | W41: IN | X41: Tower Hand | Y41: Male | Z41: 12703 | AA41: Hispanic | AB41: Single | AC41: Fully Meets | AD41: 1
A42: 3464 | B42: James | C42: Duke | D42: 43437 | E42: 44813 | F42: =IF(Table1[[#This Row],[ExitDate]],QUOTIENT(Table1[[#This Row],[ExitDate]]-Table1[[#This Row],[StartDate]],365/12),"") -> 45 | G42: =IF(Table1[[#This Row],[ExitDate]], "Attrition", "Active") -> Attrition | H42: Area Sales Manager | I42: Mark Harris | J42: james.duke@bilearner.com | K42: PYZ | L42: Active | M42: Contract | N42: Zone B | O42: Full-Time | P42: Involuntary | Q42: Stuff different color how. | R42: Sales | S42: Shop (Fleet) | T42: 35963 | U42: =YEARFRAC(Table1[[#This Row],[DOB]],TODAY()) -> 27.516667 | V42: {=_xlfn.IFS(Table1[[#This Row],[Age]] < 30, "20-29", Table1[[#This Row],[Age]]<40,"30-39",Table1[[#This Row],[Age]]<50,"40-49",Table1[[#This Row],[Age]]<60,"50-59",Table1[[#This Row],[Age]]<70, "60-69",Table1[[#This Row],[Age]]<80, "70-79",Table1[[#This Row],[Age]]<90,"80-89")} -> 20-29 | W42: MA | X42: Mechanic | Y42: Male | Z42: 66835 | AA42: Black | AB42: Widowed | AC42: Needs Improvement | AD42: 5
A43: 3465 | B43: Willow | C43: Stuart | D43: 44508 | F43: =IF(Table1[[#This Row],[ExitDate]],QUOTIENT(Table1[[#This Row],[ExitDate]]-Table1[[#This Row],[StartDate]],365/12),"") | G43: =IF(Table1[[#This Row],[ExitDate]], "Attrition", "Active") -> Active | H43: Area Sales Manager | I43: Elizabeth Tapia | J43: willow.stuart@bilearner.com | K43: WBL | L43: Active | M43: Full-Time | N43: Zone B | O43: Full-Time | P43: Unk | R43: Sales | S43: General - Con | T43: 22653 | U43: =YEARFRAC(Table1[[#This Row],[DOB]],TODAY()) -> 63.961111 | V43: {=_xlfn.IFS(Table1[[#This Row],[Age]] < 30, "20-29", Table1[[#This Row],[Age]]<40,"30-39",Table1[[#This Row],[Age]]<50,"40-49",Table1[[#This Row],[Age]]<60,"50-59",Table1[[#This Row],[Age]]<70, "60-69",Table1[[#This Row],[Age]]<80, "70-79",Table1[[#This Row],[Age]]<90,"80-89")} -> 60-69 | W43: MA | X43: Flagger | Y43: Male | Z43: 66150 | AA43: Asian | AB43: Divorced | AC43: Needs Improvement | AD43: 3
A44: 3466 | B44: Clayton | C44: Walker | D44: 44664 | E44: 45026 | F44: =IF(Table1[[#This Row],[ExitDate]],QUOTIENT(Table1[[#This Row],[ExitDate]]-Table1[[#This Row],[StartDate]],365/12),"") -> 11 | G44: =IF(Table1[[#This Row],[ExitDate]], "Attrition", "Active") -> Attrition | H44: Area Sales Manager | I44: Jon Holden | J44: clayton.walker@bilearner.com | K44: PYZ | L44: Active | M44: Part-Time | N44: Zone C | O44: Full-Time | P44: Retirement | Q44: Sign figure employee card education. | R44: IT/IS | S44: Aerial | T44: 28881 | U44: =YEARFRAC(Table1[[#This Row],[DOB]],TODAY()) -> 46.908333 | V44: {=_xlfn.IFS(Table1[[#This Row],[Age]] < 30, "20-29", Table1[[#This Row],[Age]]<40,"30-39",Table1[[#This Row],[Age]]<50,"40-49",Table1[[#This Row],[Age]]<60,"50-59",Table1[[#This Row],[Age]]<70, "60-69",Table1[[#This Row],[Age]]<80, "70-79",Table1[[#This Row],[Age]]<90,"80-89")} -> 40-49 | W44: KY | X44: Supervisor | Y44: Male | Z44: 64288 | AA44: Other | AB44: Married | AC44: Exceeds | AD44: 4
A45: 3467 | B45: Celia | C45: Curtis | D45: 43957 | F45: =IF(Table1[[#This Row],[ExitDate]],QUOTIENT(Table1[[#This Row],[ExitDate]]-Table1[[#This Row],[StartDate]],365/12),"") | G45: =IF(Table1[[#This Row],[ExitDate]], "Attrition", "Active") -> Active | H45: Area Sales Manager | I45: Michael Odonnell | J45: celia.curtis@bilearner.com | K45: WBL | L45: Active | M45: Contract | N45: Zone A | O45: Part-Time | P45: Unk | R45: Sales | S45: Fielders | T45: 31911 | U45: =YEARFRAC(Table1[[#This Row],[DOB]],TODAY()) -> 38.608333 | V45: {=_xlfn.IFS(Table1[[#This Row],[Age]] < 30, "20-29", Table1[[#This Row],[Age]]<40,"30-39",Table1[[#This Row],[Age]]<50,"40-49",Table1[[#This Row],[Age]]<60,"50-59",Table1[[#This Row],[Age]]<70, "60-69",Table1[[#This Row],[Age]]<80, "70-79",Table1[[#This Row],[Age]]<90,"80-89")} -> 30-39 | W45: KY | X45: Engineer | Y45: Female | Z45: 94333 | AA45: Asian | AB45: Divorced | AC45: Exceeds | AD45: 1
A46: 3468 | B46: Valentin | C46: Reilly | D46: 43717 | F46: =IF(Table1[[#This Row],[ExitDate]],QUOTIENT(Table1[[#This Row],[ExitDate]]-Table1[[#This Row],[StartDate]],365/12),"") | G46: =IF(Table1[[#This Row],[ExitDate]], "Attrition", "Active") -> Active | H46: Area Sales Manager | I46: Andres Parker | J46: valentin.reilly@bilearner.com | K46: NEL | L46: Active | M46: Contract | N46: Zone B | O46: Temporary | P46: Unk | R46: Sales | S46: Wireline Construction | T46: 35911 | U46: =YEARFRAC(Table1[[#This Row],[DOB]],TODAY()) -> 27.658333 | V46: {=_xlfn.IFS(Table1[[#This Row],[Age]] < 30, "20-29", Table1[[#This Row],[Age]]<40,"30-39",Table1[[#This Row],[Age]]<50,"40-49",Table1[[#This Row],[Age]]<60,"50-59",Table1[[#This Row],[Age]]<70, "60-69",Table1[[#This Row],[Age]]<80, "70-79",Table1[[#This Row],[Age]]<90,"80-89")} -> 20-29 | W46: KY | X46: Foreman | Y46: Female | Z46: 45453 | AA46: Black | AB46: Single | AC46: Fully Meets | AD46: 4
A47: 3469 | B47: Ryland | C47: Shepherd | D47: 44041 | E47: 44931 | F47: =IF(Table1[[#This Row],[ExitDate]],QUOTIENT(Table1[[#This Row],[ExitDate]]-Table1[[#This Row],[StartDate]],365/12),"") -> 29 | G47: =IF(Table1[[#This Row],[ExitDate]], "Attrition", "Active") -> Attrition | H47: Area Sales Manager | I47: James Berry | J47: ryland.shepherd@bilearner.com | K47: PL | L47: Future Start | M47: Contract | N47: Zone B | O47: Full-Time | P47: Resignation | Q47: Right cut matter arrive difference. | R47: Sales | S47: Field Operations | T47: 16489 | U47: =YEARFRAC(Table1[[#This Row],[DOB]],TODAY()) -> 80.838889 | V47: {=_xlfn.IFS(Table1[[#This Row],[Age]] < 30, "20-29", Table1[[#This Row],[Age]]<40,"30-39",Table1[[#This Row],[Age]]<50,"40-49",Table1[[#This Row],[Age]]<60,"50-59",Table1[[#This Row],[Age]]<70, "60-69",Table1[[#This Row],[Age]]<80, "70-79",Table1[[#This Row],[Age]]<90,"80-89")} -> 80-89 | W47: TX | X47: Driver | Y47: Female | Z47: 81905 | AA47: Asian | AB47: Divorced | AC47: Needs Improvement | AD47: 3
A48: 3470 | B48: Esteban | C48: Gilbert | D48: 43418 | E48: 43766 | F48: =IF(Table1[[#This Row],[ExitDate]],QUOTIENT(Table1[[#This Row],[ExitDate]]-Table1[[#This Row],[StartDate]],365/12),"") -> 11 | G48: =IF(Table1[[#This Row],[ExitDate]], "Attrition", "Active") -> Attrition | H48: Area Sales Manager | I48: Gail Ali | J48: esteban.gilbert@bilearner.com | K48: BPC | L48: Future Start | M48: Contract | N48: Zone C | O48: Part-Time | P48: Retirement | Q48: Speak professor statement result. | R48: Sales | S48: Field Operations | T48: 35581 | U48: =YEARFRAC(Table1[[#This Row],[DOB]],TODAY()) -> 28.563889 | V48: {=_xlfn.IFS(Table1[[#This Row],[Age]] < 30, "20-29", Table1[[#This Row],[Age]]<40,"30-39",Table1[[#This Row],[Age]]<50,"40-49",Table1[[#This Row],[Age]]<60,"50-59",Table1[[#This Row],[Age]]<70, "60-69",Table1[[#This Row],[Age]]<80, "70-79",Table1[[#This Row],[Age]]<90,"80-89")} -> 20-29 | W48: TX | X48: Technician | Y48: Female | Z48: 12491 | AA48: Black | AB48: Married | AC48: Needs Improvement | AD48: 3
A49: 3471 | B49: Jonathan | C49: Adkins | D49: 43890 | F49: =IF(Table1[[#This Row],[ExitDate]],QUOTIENT(Table1[[#This Row],[ExitDate]]-Table1[[#This Row],[StartDate]],365/12),"") | G49: =IF(Table1[[#This Row],[ExitDate]], "Attrition", "Active") -> Active | H49: Area Sales Manager | I49: John Marshall | J49: jonathan.adkins@bilearner.com | K49: CCDR | L49: Active | M49: Part-Time | N49: Zone C | O49: Temporary | P49: Unk | R49: Sales | S49: Field Operations | T49: 24475 | U49: =YEARFRAC(Table1[[#This Row],[DOB]],TODAY()) -> 58.972222 | V49: {=_xlfn.IFS(Table1[[#This Row],[Age]] < 30, "20-29", Table1[[#This Row],[Age]]<40,"30-39",Table1[[#This Row],[Age]]<50,"40-49",Table1[[#This Row],[Age]]<60,"50-59",Table1[[#This Row],[Age]]<70, "60-69",Table1[[#This Row],[Age]]<80, "70-79",Table1[[#This Row],[Age]]<90,"80-89")} -> 50-59 | W49: TX | X49: Foreman | Y49: Male | Z49: 64350 | AA49: Asian | AB49: Married | AC49: Fully Meets | AD49: 4
A50: 3472 | B50: Nevaeh | C50: Soto | D50: 44941 | F50: =IF(Table1[[#This Row],[ExitDate]],QUOTIENT(Table1[[#This Row],[ExitDate]]-Table1[[#This Row],[StartDate]],365/12),"") | G50: =IF(Table1[[#This Row],[ExitDate]], "Attrition", "Active") -> Active | H50: Area Sales Manager | I50: Jessica Chang | J50: nevaeh.soto@bilearner.com | K50: SVG | L50: Active | M50: Contract | N50: Zone C | O50: Full-Time | P50: Unk | R50: Sales | S50: Project Management - Con | T50: 29963 | U50: =YEARFRAC(Table1[[#This Row],[DOB]],TODAY()) -> 43.947222 | V50: {=_xlfn.IFS(Table1[[#This Row],[Age]] < 30, "20-29", Table1[[#This Row],[Age]]<40,"30-39",Table1[[#This Row],[Age]]<50,"40-49",Table1[[#This Row],[Age]]<60,"50-59",Table1[[#This Row],[Age]]<70, "60-69",Table1[[#This Row],[Age]]<80, "70-79",Table1[[#This Row],[Age]]<90,"80-89")} -> 40-49 | W50: TX | X50: Director | Y50: Male | Z50: 74124 | AA50: Other | AB50: Married | AC50: Exceeds | AD50: 4
A51: 3473 | B51: Chaim | C51: Mata | D51: 45106 | F51: =IF(Table1[[#This Row],[ExitDate]],QUOTIENT(Table1[[#This Row],[ExitDate]]-Table1[[#This Row],[StartDate]],365/12),"") | G51: =IF(Table1[[#This Row],[ExitDate]], "Attrition", "Active") -> Active | H51: Area Sales Manager | I51: Desiree Vang | J51: chaim.mata@bilearner.com | K51: EW | L51: Active | M51: Part-Time | N51: Zone A | O51: Temporary | P51: Unk | R51: Sales | S51: Shop (Fleet) | T51: 18537 | U51: =YEARFRAC(Table1[[#This Row],[DOB]],TODAY()) -> 75.227778 | V51: {=_xlfn.IFS(Table1[[#This Row],[Age]] < 30, "20-29", Table1[[#This Row],[Age]]<40,"30-39",Table1[[#This Row],[Age]]<50,"40-49",Table1[[#This Row],[Age]]<60,"50-59",Table1[[#This Row],[Age]]<70, "60-69",Table1[[#This Row],[Age]]<80, "70-79",Table1[[#This Row],[Age]]<90,"80-89")} -> 70-79 | W51: CO | X51: Manager | Y51: Male | Z51: 33379 | AA51: Hispanic | AB51: Widowed | AC51: Exceeds | AD51: 2
A52: 3474 | B52: Arely | C52: Patton | D52: 43899 | F52: =IF(Table1[[#This Row],[ExitDate]],QUOTIENT(Table1[[#This Row],[ExitDate]]-Table1[[#This Row],[StartDate]],365/12),"") | G52: =IF(Table1[[#This Row],[ExitDate]], "Attrition", "Active") -> Active | H52: Area Sales Manager | I52: Andrew Goodman | J52: arely.patton@bilearner.com | K52: MSC | L52: Active | M52: Full-Time | N52: Zone A | O52: Temporary | P52: Unk | R52: Sales | S52: Catv | T52: 24092 | U52: =YEARFRAC(Table1[[#This Row],[DOB]],TODAY()) -> 60.019444 | V52: {=_xlfn.IFS(Table1[[#This Row],[Age]] < 30, "20-29", Table1[[#This Row],[Age]]<40,"30-39",Table1[[#This Row],[Age]]<50,"40-49",Table1[[#This Row],[Age]]<60,"50-59",Table1[[#This Row],[Age]]<70, "60-69",Table1[[#This Row],[Age]]<80, "70-79",Table1[[#This Row],[Age]]<90,"80-89")} -> 60-69 | W52: CO | X52: Laborer | Y52: Male | Z52: 34481 | AA52: Other | AB52: Divorced | AC52: Fully Meets | AD52: 2
A53: 3475 | B53: Vance | C53: Trujillo | D53: 44460 | E53: 45029 | F53: =IF(Table1[[#This Row],[ExitDate]],QUOTIENT(Table1[[#This Row],[ExitDate]]-Table1[[#This Row],[StartDate]],365/12),"") -> 18 | G53: =IF(Table1[[#This Row],[ExitDate]], "Attrition", "Active") -> Attrition | H53: Area Sales Manager | I53: Rebecca Simpson | J53: vance.trujillo@bilearner.com | K53: TNS | L53: Active | M53: Full-Time | N53: Zone C | O53: Temporary | P53: Resignation | Q53: Expert challenge education air none money wide. | R53: Sales | S53: General - Con | T53: 21179 | U53: =YEARFRAC(Table1[[#This Row],[DOB]],TODAY()) -> 67.994444 | V53: {=_xlfn.IFS(Table1[[#This Row],[Age]] < 30, "20-29", Table1[[#This Row],[Age]]<40,"30-39",Table1[[#This Row],[Age]]<50,"40-49",Table1[[#This Row],[Age]]<60,"50-59",Table1[[#This Row],[Age]]<70, "60-69",Table1[[#This Row],[Age]]<80, "70-79",Table1[[#This Row],[Age]]<90,"80-89")} -> 60-69 | W53: IN | X53: Foreman | Y53: Male | Z53: 90406 | AA53: Asian | AB53: Widowed | AC53: Fully Meets | AD53: 2
A54: 3476 | B54: Charlie | C54: Koch | D54: 45089 | E54: 45113 | F54: =IF(Table1[[#This Row],[ExitDate]],QUOTIENT(Table1[[#This Row],[ExitDate]]-Table1[[#This Row],[StartDate]],365/12),"") -> 0 | G54: =IF(Table1[[#This Row],[ExitDate]], "Attrition", "Active") -> Attrition | H54: Area Sales Manager | I54: Samantha Cardenas | J54: charlie.koch@bilearner.com | K54: PYZ | L54: Active | M54: Part-Time | N54: Zone A | O54: Temporary | P54: Voluntary | Q54: Buy become improve guess business know. | R54: Sales | S54: Fielders | T54: 16608 | U54: =YEARFRAC(Table1[[#This Row],[DOB]],TODAY()) -> 80.508333 | V54: {=_xlfn.IFS(Table1[[#This Row],[Age]] < 30, "20-29", Table1[[#This Row],[Age]]<40,"30-39",Table1[[#This Row],[Age]]<50,"40-49",Table1[[#This Row],[Age]]<60,"50-59",Table1[[#This Row],[Age]]<70, "60-69",Table1[[#This Row],[Age]]<80, "70-79",Table1[[#This Row],[Age]]<90,"80-89")} -> 80-89 | W54: MA | X54: Engineer | Y54: Male | Z54: 95774 | AA54: Asian | AB54: Divorced | AC54: Needs Improvement | AD54: 2
A55: 3477 | B55: Sonny | C55: Horne | D55: 43562 | F55: =IF(Table1[[#This Row],[ExitDate]],QUOTIENT(Table1[[#This Row],[ExitDate]]-Table1[[#This Row],[StartDate]],365/12),"") | G55: =IF(Table1[[#This Row],[ExitDate]], "Attrition", "Active") -> Active | H55: Area Sales Manager | I55: Nancy Johnson | J55: sonny.horne@bilearner.com | K55: PYZ | L55: Active | M55: Part-Time | N55: Zone A | O55: Full-Time | P55: Unk | R55: IT/IS | S55: Aerial | T55: 25540 | U55: =YEARFRAC(Table1[[#This Row],[DOB]],TODAY()) -> 56.055556 | V55: {=_xlfn.IFS(Table1[[#This Row],[Age]] < 30, "20-29", Table1[[#This Row],[Age]]<40,"30-39",Table1[[#This Row],[Age]]<50,"40-49",Table1[[#This Row],[Age]]<60,"50-59",Table1[[#This Row],[Age]]<70, "60-69",Table1[[#This Row],[Age]]<80, "70-79",Table1[[#This Row],[Age]]<90,"80-89")} -> 50-59 | W55: KY | X55: Laborer | Y55: Female | Z55: 16058 | AA55: Asian | AB55: Widowed | AC55: Needs Improvement | AD55: 2
A56: 3478 | B56: Thomas | C56: Chandler | D56: 43360 | E56: 43474 | F56: =IF(Table1[[#This Row],[ExitDate]],QUOTIENT(Table1[[#This Row],[ExitDate]]-Table1[[#This Row],[StartDate]],365/12),"") -> 3 | G56: =IF(Table1[[#This Row],[ExitDate]], "Attrition", "Active") -> Attrition | H56: Area Sales Manager | I56: Richard Hodges | J56: thomas.chandler@bilearner.com | K56: WBL | L56: Active | M56: Full-Time | N56: Zone C | O56: Temporary | P56: Resignation | Q56: Read family dark scene scene guess. | R56: Sales | S56: Wireline Construction | T56: 21103 | U56: =YEARFRAC(Table1[[#This Row],[DOB]],TODAY()) -> 68.202778 | V56: {=_xlfn.IFS(Table1[[#This Row],[Age]] < 30, "20-29", Table1[[#This Row],[Age]]<40,"30-39",Table1[[#This Row],[Age]]<50,"40-49",Table1[[#This Row],[Age]]<60,"50-59",Table1[[#This Row],[Age]]<70, "60-69",Table1[[#This Row],[Age]]<80, "70-79",Table1[[#This Row],[Age]]<90,"80-89")} -> 60-69 | W56: KY | X56: Groundman | Y56: Female | Z56: 45149 | AA56: Hispanic | AB56: Married | AC56: Fully Meets | AD56: 2
A57: 3479 | B57: Sarai | C57: Stone | D57: 44775 | E57: 45018 | F57: =IF(Table1[[#This Row],[ExitDate]],QUOTIENT(Table1[[#This Row],[ExitDate]]-Table1[[#This Row],[StartDate]],365/12),"") -> 7 | G57: =IF(Table1[[#This Row],[ExitDate]], "Attrition", "Active") -> Attrition | H57: Area Sales Manager | I57: Madison Wilson | J57: sarai.stone@bilearner.com | K57: NEL | L57: Active | M57: Contract | N57: Zone A | O57: Part-Time | P57: Involuntary | Q57: Somebody great could yet. | R57: Sales | S57: Project Management - Con | T57: 22783 | U57: =YEARFRAC(Table1[[#This Row],[DOB]],TODAY()) -> 63.6 | V57: {=_xlfn.IFS(Table1[[#This Row],[Age]] < 30, "20-29", Table1[[#This Row],[Age]]<40,"30-39",Table1[[#This Row],[Age]]<50,"40-49",Table1[[#This Row],[Age]]<60,"50-59",Table1[[#This Row],[Age]]<70, "60-69",Table1[[#This Row],[Age]]<80, "70-79",Table1[[#This Row],[Age]]<90,"80-89")} -> 60-69 | W57: TX | X57: Technician | Y57: Female | Z57: 96336 | AA57: Hispanic | AB57: Widowed | AC57: Fully Meets | AD57: 2
A58: 3480 | B58: Jerimiah | C58: Harmon | D58: 44812 | E58: 44850 | F58: =IF(Table1[[#This Row],[ExitDate]],QUOTIENT(Table1[[#This Row],[ExitDate]]-Table1[[#This Row],[StartDate]],365/12),"") -> 1 | G58: =IF(Table1[[#This Row],[ExitDate]], "Attrition", "Active") -> Attrition | H58: Area Sales Manager | I58: Eric King | J58: jerimiah.harmon@bilearner.com | K58: PL | L58: Future Start | M58: Full-Time | N58: Zone C | O58: Temporary | P58: Retirement | Q58: View vote contain within fight cup party war. | R58: Sales | S58: Catv | T58: 17023 | U58: =YEARFRAC(Table1[[#This Row],[DOB]],TODAY()) -> 79.372222 | V58: {=_xlfn.IFS(Table1[[#This Row],[Age]] < 30, "20-29", Table1[[#This Row],[Age]]<40,"30-39",Table1[[#This Row],[Age]]<50,"40-49",Table1[[#This Row],[Age]]<60,"50-59",Table1[[#This Row],[Age]]<70, "60-69",Table1[[#This Row],[Age]]<80, "70-79",Table1[[#This Row],[Age]]<90,"80-89")} -> 70-79 | W58: TX | X58: Supervisor | Y58: Female | Z58: 75671 | AA58: Black | AB58: Widowed | AC58: Fully Meets | AD58: 1
A59: 3481 | B59: Leland | C59: Allen | D59: 43531 | E59: 44347 | F59: =IF(Table1[[#This Row],[ExitDate]],QUOTIENT(Table1[[#This Row],[ExitDate]]-Table1[[#This Row],[StartDate]],365/12),"") -> 26 | G59: =IF(Table1[[#This Row],[ExitDate]], "Attrition", "Active") -> Attrition | H59: Area Sales Manager | I59: Brandon Harris | J59: leland.allen@bilearner.com | K59: BPC | L59: Future Start | M59: Full-Time | N59: Zone C | O59: Part-Time | P59: Voluntary | Q59: Buy house certain wrong research chair. | R59: Sales | S59: Wireline Construction | T59: 24087 | U59: =YEARFRAC(Table1[[#This Row],[DOB]],TODAY()) -> 60.033333 | V59: {=_xlfn.IFS(Table1[[#This Row],[Age]] < 30, "20-29", Table1[[#This Row],[Age]]<40,"30-39",Table1[[#This Row],[Age]]<50,"40-49",Table1[[#This Row],[Age]]<60,"50-59",Table1[[#This Row],[Age]]<70, "60-69",Table1[[#This Row],[Age]]<80, "70-79",Table1[[#This Row],[Age]]<90,"80-89")} -> 60-69 | W59: TX | X59: Splicer | Y59: Male | Z59: 61149 | AA59: Other | AB59: Widowed | AC59: Fully Meets | AD59: 4
A60: 3482 | B60: Cristal | C60: Bolton | D60: 43767 | E60: 44234 | F60: =IF(Table1[[#This Row],[ExitDate]],QUOTIENT(Table1[[#This Row],[ExitDate]]-Table1[[#This Row],[StartDate]],365/12),"") -> 15 | G60: =IF(Table1[[#This Row],[ExitDate]], "Attrition", "Active") -> Attrition | H60: Area Sales Manager | I60: Matthew Flores | J60: cristal.bolton@bilearner.com | K60: CCDR | L60: Future Start | M60: Full-Time | N60: Zone A | O60: Temporary | P60: Resignation | Q60: Miss onto none our discussion year. | R60: Sales | S60: Catv | T60: 32915 | U60: =YEARFRAC(Table1[[#This Row],[DOB]],TODAY()) -> 35.866667 | V60: {=_xlfn.IFS(Table1[[#This Row],[Age]] < 30, "20-29", Table1[[#This Row],[Age]]<40,"30-39",Table1[[#This Row],[Age]]<50,"40-49",Table1[[#This Row],[Age]]<60,"50-59",Table1[[#This Row],[Age]]<70, "60-69",Table1[[#This Row],[Age]]<80, "70-79",Table1[[#This Row],[Age]]<90,"80-89")} -> 30-39 | W60: TX | X60: Lineman | Y60: Male | Z60: 57302 | AA60: Asian | AB60: Divorced | AC60: Needs Improvement | AD60: 2
A61: 3483 | B61: Jaslene | C61: Harding | D61: 44465 | F61: =IF(Table1[[#This Row],[ExitDate]],QUOTIENT(Table1[[#This Row],[ExitDate]]-Table1[[#This Row],[StartDate]],365/12),"") | G61: =IF(Table1[[#This Row],[ExitDate]], "Attrition", "Active") -> Active | H61: Area Sales Manager | I61: Krystal Hamilton | J61: jaslene.harding@bilearner.com | K61: SVG | L61: Active | M61: Part-Time | N61: Zone B | O61: Temporary | P61: Unk | R61: Sales | S61: Project Management - Con | T61: 23547 | U61: =YEARFRAC(Table1[[#This Row],[DOB]],TODAY()) -> 61.511111 | V61: {=_xlfn.IFS(Table1[[#This Row],[Age]] < 30, "20-29", Table1[[#This Row],[Age]]<40,"30-39",Table1[[#This Row],[Age]]<50,"40-49",Table1[[#This Row],[Age]]<60,"50-59",Table1[[#This Row],[Age]]<70, "60-69",Table1[[#This Row],[Age]]<80, "70-79",Table1[[#This Row],[Age]]<90,"80-89")} -> 60-69 | W61: CO | X61: Coordinator | Y61: Male | Z61: 42605 | AA61: Asian | AB61: Widowed | AC61: Fully Meets | AD61: 1
A62: 3484 | B62: Albert | C62: Gonzalez | D62: 43341 | F62: =IF(Table1[[#This Row],[ExitDate]],QUOTIENT(Table1[[#This Row],[ExitDate]]-Table1[[#This Row],[StartDate]],365/12),"") | G62: =IF(Table1[[#This Row],[ExitDate]], "Attrition", "Active") -> Active | H62: Area Sales Manager | I62: Amber Hernandez | J62: albert.gonzalez@bilearner.com | K62: EW | L62: Active | M62: Part-Time | N62: Zone B | O62: Full-Time | P62: Unk | R62: Sales | S62: General - Con | T62: 34898 | U62: =YEARFRAC(Table1[[#This Row],[DOB]],TODAY()) -> 30.430556 | V62: {=_xlfn.IFS(Table1[[#This Row],[Age]] < 30, "20-29", Table1[[#This Row],[Age]]<40,"30-39",Table1[[#This Row],[Age]]<50,"40-49",Table1[[#This Row],[Age]]<60,"50-59",Table1[[#This Row],[Age]]<70, "60-69",Table1[[#This Row],[Age]]<80, "70-79",Table1[[#This Row],[Age]]<90,"80-89")} -> 30-39 | W62: CO | X62: Model Assistant | Y62: Male | Z62: 64036 | AA62: Other | AB62: Single | AC62: Fully Meets | AD62: 4
A63: 3485 | B63: Jaiden | C63: Johnson | D63: 44495 | F63: =IF(Table1[[#This Row],[ExitDate]],QUOTIENT(Table1[[#This Row],[ExitDate]]-Table1[[#This Row],[StartDate]],365/12),"") | G63: =IF(Table1[[#This Row],[ExitDate]], "Attrition", "Active") -> Active | H63: Area Sales Manager | I63: Patricia Smith | J63: jaiden.johnson@bilearner.com | K63: MSC | L63: Active | M63: Contract | N63: Zone C | O63: Full-Time | P63: Unk | R63: Sales | S63: Field Operations | T63: 34568 | U63: =YEARFRAC(Table1[[#This Row],[DOB]],TODAY()) -> 31.336111 | V63: {=_xlfn.IFS(Table1[[#This Row],[Age]] < 30, "20-29", Table1[[#This Row],[Age]]<40,"30-39",Table1[[#This Row],[Age]]<50,"40-49",Table1[[#This Row],[Age]]<60,"50-59",Table1[[#This Row],[Age]]<70, "60-69",Table1[[#This Row],[Age]]<80, "70-79",Table1[[#This Row],[Age]]<90,"80-89")} -> 30-39 | W63: CO | X63: Laborer | Y63: Male | Z63: 23173 | AA63: White | AB63: Widowed | AC63: Fully Meets | AD63: 5
A64: 3486 | B64: Brendon | C64: Mcconnell | D64: 44865 | E64: 45085 | F64: =IF(Table1[[#This Row],[ExitDate]],QUOTIENT(Table1[[#This Row],[ExitDate]]-Table1[[#This Row],[StartDate]],365/12),"") -> 7 | G64: =IF(Table1[[#This Row],[ExitDate]], "Attrition", "Active") -> Attrition | H64: Area Sales Manager | I64: Victoria Krause | J64: brendon.mcconnell@bilearner.com | K64: TNS | L64: Active | M64: Part-Time | N64: Zone C | O64: Temporary | P64: Involuntary | Q64: Nature finish modern push former American. | R64: Sales | S64: Fielders | T64: 33191 | U64: =YEARFRAC(Table1[[#This Row],[DOB]],TODAY()) -> 35.108333 | V64: {=_xlfn.IFS(Table1[[#This Row],[Age]] < 30, "20-29", Table1[[#This Row],[Age]]<40,"30-39",Table1[[#This Row],[Age]]<50,"40-49",Table1[[#This Row],[Age]]<60,"50-59",Table1[[#This Row],[Age]]<70, "60-69",Table1[[#This Row],[Age]]<80, "70-79",Table1[[#This Row],[Age]]<90,"80-89")} -> 30-39 | W64: IN | X64: Engineer | Y64: Male | Z64: 19665 | AA64: Other | AB64: Widowed | AC64: Fully Meets | AD64: 4
A65: 3487 | B65: Kimora | C65: Parsons | D65: 45000 | F65: =IF(Table1[[#This Row],[ExitDate]],QUOTIENT(Table1[[#This Row],[ExitDate]]-Table1[[#This Row],[StartDate]],365/12),"") | G65: =IF(Table1[[#This Row],[ExitDate]], "Attrition", "Active") -> Active | H65: Area Sales Manager | I65: Jesse Hunt | J65: kimora.parsons@bilearner.com | K65: BPC | L65: Active | M65: Contract | N65: Zone B | O65: Part-Time | P65: Unk | R65: Sales | S65: General - Sga | T65: 34366 | U65: =YEARFRAC(Table1[[#This Row],[DOB]],TODAY()) -> 31.894444 | V65: {=_xlfn.IFS(Table1[[#This Row],[Age]] < 30, "20-29", Table1[[#This Row],[Age]]<40,"30-39",Table1[[#This Row],[Age]]<50,"40-49",Table1[[#This Row],[Age]]<60,"50-59",Table1[[#This Row],[Age]]<70, "60-69",Table1[[#This Row],[Age]]<80, "70-79",Table1[[#This Row],[Age]]<90,"80-89")} -> 30-39 | W65: KY | X65: Administrator | Y65: Female | Z65: 41161 | AA65: Other | AB65: Divorced | AC65: Fully Meets | AD65: 4
A66: 3488 | B66: Willie | C66: Patterson | D66: 44813 | F66: =IF(Table1[[#This Row],[ExitDate]],QUOTIENT(Table1[[#This Row],[ExitDate]]-Table1[[#This Row],[StartDate]],365/12),"") | G66: =IF(Table1[[#This Row],[ExitDate]], "Attrition", "Active") -> Active | H66: Area Sales Manager | I66: Shane Jones | J66: willie.patterson@bilearner.com | K66: CCDR | L66: Active | M66: Contract | N66: Zone B | O66: Full-Time | P66: Unk | R66: Sales | S66: Wireline Construction | T66: 35746 | U66: =YEARFRAC(Table1[[#This Row],[DOB]],TODAY()) -> 28.113889 | V66: {=_xlfn.IFS(Table1[[#This Row],[Age]] < 30, "20-29", Table1[[#This Row],[Age]]<40,"30-39",Table1[[#This Row],[Age]]<50,"40-49",Table1[[#This Row],[Age]]<60,"50-59",Table1[[#This Row],[Age]]<70, "60-69",Table1[[#This Row],[Age]]<80, "70-79",Table1[[#This Row],[Age]]<90,"80-89")} -> 20-29 | W66: KY | X66: Lineman | Y66: Female | Z66: 52499 | AA66: Asian | AB66: Single | AC66: Fully Meets | AD66: 2
A67: 3489 | B67: Devyn | C67: Powers | D67: 44624 | F67: =IF(Table1[[#This Row],[ExitDate]],QUOTIENT(Table1[[#This Row],[ExitDate]]-Table1[[#This Row],[StartDate]],365/12),"") | G67: =IF(Table1[[#This Row],[ExitDate]], "Attrition", "Active") -> Active | H67: Area Sales Manager | I67: Jessica Murphy | J67: devyn.powers@bilearner.com | K67: EW | L67: Active | M67: Part-Time | N67: Zone A | O67: Temporary | P67: Unk | R67: Sales | S67: Field Operations | T67: 19481 | U67: =YEARFRAC(Table1[[#This Row],[DOB]],TODAY()) -> 72.641667 | V67: {=_xlfn.IFS(Table1[[#This Row],[Age]] < 30, "20-29", Table1[[#This Row],[Age]]<40,"30-39",Table1[[#This Row],[Age]]<50,"40-49",Table1[[#This Row],[Age]]<60,"50-59",Table1[[#This Row],[Age]]<70, "60-69",Table1[[#This Row],[Age]]<80, "70-79",Table1[[#This Row],[Age]]<90,"80-89")} -> 70-79 | W67: TX | X67: Laborer | Y67: Female | Z67: 25634 | AA67: Black | AB67: Divorced | AC67: Fully Meets | AD67: 2
A68: 3490 | B68: Weston | C68: Preston | D68: 43507 | F68: =IF(Table1[[#This Row],[ExitDate]],QUOTIENT(Table1[[#This Row],[ExitDate]]-Table1[[#This Row],[StartDate]],365/12),"") | G68: =IF(Table1[[#This Row],[ExitDate]], "Attrition", "Active") -> Active | H68: Area Sales Manager | I68: Crystal Wallace | J68: weston.preston@bilearner.com | K68: MSC | L68: Active | M68: Part-Time | N68: Zone A | O68: Part-Time | P68: Unk | R68: Sales | S68: General - Sga | T68: 33429 | U68: =YEARFRAC(Table1[[#This Row],[DOB]],TODAY()) -> 34.452778 | V68: {=_xlfn.IFS(Table1[[#This Row],[Age]] < 30, "20-29", Table1[[#This Row],[Age]]<40,"30-39",Table1[[#This Row],[Age]]<50,"40-49",Table1[[#This Row],[Age]]<60,"50-59",Table1[[#This Row],[Age]]<70, "60-69",Table1[[#This Row],[Age]]<80, "70-79",Table1[[#This Row],[Age]]<90,"80-89")} -> 30-39 | W68: TX | X68: Director | Y68: Female | Z68: 37965 | AA68: Hispanic | AB68: Divorced | AC68: Fully Meets | AD68: 2
A69: 3491 | B69: Lennon | C69: Buchanan | D69: 44222 | F69: =IF(Table1[[#This Row],[ExitDate]],QUOTIENT(Table1[[#This Row],[ExitDate]]-Table1[[#This Row],[StartDate]],365/12),"") | G69: =IF(Table1[[#This Row],[ExitDate]], "Attrition", "Active") -> Active | H69: Area Sales Manager | I69: Tina Nelson | J69: lennon.buchanan@bilearner.com | K69: NEL | L69: Active | M69: Contract | N69: Zone B | O69: Full-Time | P69: Unk | R69: Sales | S69: Field Operations | T69: 26817 | U69: =YEARFRAC(Table1[[#This Row],[DOB]],TODAY()) -> 52.558333 | V69: {=_xlfn.IFS(Table1[[#This Row],[Age]] < 30, "20-29", Table1[[#This Row],[Age]]<40,"30-39",Table1[[#This Row],[Age]]<50,"40-49",Table1[[#This Row],[Age]]<60,"50-59",Table1[[#This Row],[Age]]<70, "60-69",Table1[[#This Row],[Age]]<80, "70-79",Table1[[#This Row],[Age]]<90,"80-89")} -> 50-59 | W69: TX | X69: Driver | Y69: Male | Z69: 39504 | AA69: White | AB69: Widowed | AC69: Fully Meets | AD69: 5
A70: 3492 | B70: Vicente | C70: Merritt | D70: 43795 | F70: =IF(Table1[[#This Row],[ExitDate]],QUOTIENT(Table1[[#This Row],[ExitDate]]-Table1[[#This Row],[StartDate]],365/12),"") | G70: =IF(Table1[[#This Row],[ExitDate]], "Attrition", "Active") -> Active | H70: Area Sales Manager | I70: Ashley Smith | J70: vicente.merritt@bilearner.com | K70: PL | L70: Active | M70: Full-Time | N70: Zone C | O70: Full-Time | P70: Unk | R70: Sales | S70: General - Con | T70: 33977 | U70: =YEARFRAC(Table1[[#This Row],[DOB]],TODAY()) -> 32.958333 | V70: {=_xlfn.IFS(Table1[[#This Row],[Age]] < 30, "20-29", Table1[[#This Row],[Age]]<40,"30-39",Table1[[#This Row],[Age]]<50,"40-49",Table1[[#This Row],[Age]]<60,"50-59",Table1[[#This Row],[Age]]<70, "60-69",Table1[[#This Row],[Age]]<80, "70-79",Table1[[#This Row],[Age]]<90,"80-89")} -> 30-39 | W70: CO | X70: Clerk | Y70: Male | Z70: 31676 | AA70: Asian | AB70: Married | AC70: Fully Meets | AD70: 1
A71: 3493 | B71: Hugo | C71: Clay | D71: 43661 | F71: =IF(Table1[[#This Row],[ExitDate]],QUOTIENT(Table1[[#This Row],[ExitDate]]-Table1[[#This Row],[StartDate]],365/12),"") | G71: =IF(Table1[[#This Row],[ExitDate]], "Attrition", "Active") -> Active | H71: Area Sales Manager | I71: Eric Taylor | J71: hugo.clay@bilearner.com | K71: PYZ | L71: Active | M71: Full-Time | N71: Zone C | O71: Full-Time | P71: Unk | R71: Sales | S71: Project Management - Con | T71: 30789 | U71: =YEARFRAC(Table1[[#This Row],[DOB]],TODAY()) -> 41.683333 | V71: {=_xlfn.IFS(Table1[[#This Row],[Age]] < 30, "20-29", Table1[[#This Row],[Age]]<40,"30-39",Table1[[#This Row],[Age]]<50,"40-49",Table1[[#This Row],[Age]]<60,"50-59",Table1[[#This Row],[Age]]<70, "60-69",Table1[[#This Row],[Age]]<80, "70-79",Table1[[#This Row],[Age]]<90,"80-89")} -> 40-49 | W71: CO | X71: Project Manager | Y71: Male | Z71: 28784 | AA71: Asian | AB71: Widowed | AC71: Fully Meets | AD71: 5
A72: 3494 | B72: Cohen | C72: Raymond | D72: 44000 | F72: =IF(Table1[[#This Row],[ExitDate]],QUOTIENT(Table1[[#This Row],[ExitDate]]-Table1[[#This Row],[StartDate]],365/12),"") | G72: =IF(Table1[[#This Row],[ExitDate]], "Attrition", "Active") -> Active | H72: Area Sales Manager | I72: Jacob Snyder | J72: cohen.raymond@bilearner.com | K72: SVG | L72: Active | M72: Contract | N72: Zone B | O72: Full-Time | P72: Unk | R72: Sales | S72: General - Con | T72: 34373 | U72: =YEARFRAC(Table1[[#This Row],[DOB]],TODAY()) -> 31.875 | V72: {=_xlfn.IFS(Table1[[#This Row],[Age]] < 30, "20-29", Table1[[#This Row],[Age]]<40,"30-39",Table1[[#This Row],[Age]]<50,"40-49",Table1[[#This Row],[Age]]<60,"50-59",Table1[[#This Row],[Age]]<70, "60-69",Table1[[#This Row],[Age]]<80, "70-79",Table1[[#This Row],[Age]]<90,"80-89")} -> 30-39 | W72: CO | X72: Technician | Y72: Male | Z72: 90983 | AA72: Black | AB72: Single | AC72: Fully Meets | AD72: 4
A73: 3495 | B73: Tia | C73: Ellis | D73: 45099 | E73: 45129 | F73: =IF(Table1[[#This Row],[ExitDate]],QUOTIENT(Table1[[#This Row],[ExitDate]]-Table1[[#This Row],[StartDate]],365/12),"") -> 0 | G73: =IF(Table1[[#This Row],[ExitDate]], "Attrition", "Active") -> Attrition | H73: Area Sales Manager | I73: Daniel Cabrera | J73: tia.ellis@bilearner.com | K73: TNS | L73: Active | M73: Part-Time | N73: Zone B | O73: Temporary | P73: Retirement | Q73: Night company image able suggest. | R73: Sales | S73: Wireline Construction | T73: 33996 | U73: =YEARFRAC(Table1[[#This Row],[DOB]],TODAY()) -> 32.905556 | V73: {=_xlfn.IFS(Table1[[#This Row],[Age]] < 30, "20-29", Table1[[#This Row],[Age]]<40,"30-39",Table1[[#This Row],[Age]]<50,"40-49",Table1[[#This Row],[Age]]<60,"50-59",Table1[[#This Row],[Age]]<70, "60-69",Table1[[#This Row],[Age]]<80, "70-79",Table1[[#This Row],[Age]]<90,"80-89")} -> 30-39 | W73: IN | X73: Laborer | Y73: Male | Z73: 1115 | AA73: Other | AB73: Married | AC73: Fully Meets | AD73: 4
A74: 3496 | B74: Aspen | C74: Bentley | D74: 44532 | F74: =IF(Table1[[#This Row],[ExitDate]],QUOTIENT(Table1[[#This Row],[ExitDate]]-Table1[[#This Row],[StartDate]],365/12),"") | G74: =IF(Table1[[#This Row],[ExitDate]], "Attrition", "Active") -> Active | H74: Area Sales Manager | I74: Barbara Garcia | J74: aspen.bentley@bilearner.com | K74: WBL | L74: Active | M74: Contract | N74: Zone A | O74: Part-Time | P74: Unk | R74: Sales | S74: General - Sga | T74: 23639 | U74: =YEARFRAC(Table1[[#This Row],[DOB]],TODAY()) -> 61.261111 | V74: {=_xlfn.IFS(Table1[[#This Row],[Age]] < 30, "20-29", Table1[[#This Row],[Age]]<40,"30-39",Table1[[#This Row],[Age]]<50,"40-49",Table1[[#This Row],[Age]]<60,"50-59",Table1[[#This Row],[Age]]<70, "60-69",Table1[[#This Row],[Age]]<80, "70-79",Table1[[#This Row],[Age]]<90,"80-89")} -> 60-69 | W74: CA | X74: Administrator | Y74: Male | Z74: 72233 | AA74: Other | AB74: Widowed | AC74: Fully Meets | AD74: 5
A75: 3497 | B75: Graham | C75: Rodriguez | D75: 44538 | F75: =IF(Table1[[#This Row],[ExitDate]],QUOTIENT(Table1[[#This Row],[ExitDate]]-Table1[[#This Row],[StartDate]],365/12),"") | G75: =IF(Table1[[#This Row],[ExitDate]], "Attrition", "Active") -> Active | H75: Area Sales Manager | I75: Kendra Murray | J75: graham.rodriguez@bilearner.com | K75: TNS | L75: Active | M75: Part-Time | N75: Zone C | O75: Temporary | P75: Unk | R75: Sales | S75: Project Management - Con | T75: 29635 | U75: =YEARFRAC(Table1[[#This Row],[DOB]],TODAY()) -> 44.847222 | V75: {=_xlfn.IFS(Table1[[#This Row],[Age]] < 30, "20-29", Table1[[#This Row],[Age]]<40,"30-39",Table1[[#This Row],[Age]]<50,"40-49",Table1[[#This Row],[Age]]<60,"50-59",Table1[[#This Row],[Age]]<70, "60-69",Table1[[#This Row],[Age]]<80, "70-79",Table1[[#This Row],[Age]]<90,"80-89")} -> 40-49 | W75: OR | X75: Lineman | Y75: Female | Z75: 58210 | AA75: Hispanic | AB75: Widowed | AC75: Fully Meets | AD75: 1
A76: 3498 | B76: Joel | C76: Mcmillan | D76: 45042 | E76: 45099 | F76: =IF(Table1[[#This Row],[ExitDate]],QUOTIENT(Table1[[#This Row],[ExitDate]]-Table1[[#This Row],[StartDate]],365/12),"") -> 1 | G76: =IF(Table1[[#This Row],[ExitDate]], "Attrition", "Active") -> Attrition | H76: Area Sales Manager | I76: Peter Harvey | J76: joel.mcmillan@bilearner.com | K76: PYZ | L76: Active | M76: Full-Time | N76: Zone A | O76: Full-Time | P76: Voluntary | Q76: About allow article. For gas player magazine. | R76: Sales | S76: General - Sga | T76: 36085 | U76: =YEARFRAC(Table1[[#This Row],[DOB]],TODAY()) -> 27.183333 | V76: {=_xlfn.IFS(Table1[[#This Row],[Age]] < 30, "20-29", Table1[[#This Row],[Age]]<40,"30-39",Table1[[#This Row],[Age]]<50,"40-49",Table1[[#This Row],[Age]]<60,"50-59",Table1[[#This Row],[Age]]<70, "60-69",Table1[[#This Row],[Age]]<80, "70-79",Table1[[#This Row],[Age]]<90,"80-89")} -> 20-29 | W76: KY | X76: Laborer | Y76: Female | Z76: 36087 | AA76: White | AB76: Widowed | AC76: Fully Meets | AD76: 2
A77: 3499 | B77: Maci | C77: Frost | D77: 43368 | E77: 44550 | F77: =IF(Table1[[#This Row],[ExitDate]],QUOTIENT(Table1[[#This Row],[ExitDate]]-Table1[[#This Row],[StartDate]],365/12),"") -> 38 | G77: =IF(Table1[[#This Row],[ExitDate]], "Attrition", "Active") -> Attrition | H77: Area Sales Manager | I77: Patrick Daniel | J77: maci.frost@bilearner.com | K77: WBL | L77: Active | M77: Part-Time | N77: Zone C | O77: Temporary | P77: Involuntary | Q77: Seem hand dog. Us six beyond place fund well. | R77: Sales | S77: Field Operations | T77: 25949 | U77: =YEARFRAC(Table1[[#This Row],[DOB]],TODAY()) -> 54.936111 | V77: {=_xlfn.IFS(Table1[[#This Row],[Age]] < 30, "20-29", Table1[[#This Row],[Age]]<40,"30-39",Table1[[#This Row],[Age]]<50,"40-49",Table1[[#This Row],[Age]]<60,"50-59",Table1[[#This Row],[Age]]<70, "60-69",Table1[[#This Row],[Age]]<80, "70-79",Table1[[#This Row],[Age]]<90,"80-89")} -> 50-59 | W77: KY | X77: Technician | Y77: Female | Z77: 61457 | AA77: Asian | AB77: Widowed | AC77: Fully Meets | AD77: 5
A78: 3500 | B78: Nevaeh | C78: Lucas | D78: 43424 | E78: 44003 | F78: =IF(Table1[[#This Row],[ExitDate]],QUOTIENT(Table1[[#This Row],[ExitDate]]-Table1[[#This Row],[StartDate]],365/12),"") -> 19 | G78: =IF(Table1[[#This Row],[ExitDate]], "Attrition", "Active") -> Attrition | H78: Area Sales Manager | I78: Bryan Douglas | J78: nevaeh.lucas@bilearner.com | K78: NEL | L78: Active | M78: Full-Time | N78: Zone B | O78: Part-Time | P78: Voluntary | Q78: Game hour boy not write somebody owner. | R78: Sales | S78: Shop (Fleet) | T78: 36581 | U78: =YEARFRAC(Table1[[#This Row],[DOB]],TODAY()) -> 25.827778 | V78: {=_xlfn.IFS(Table1[[#This Row],[Age]] < 30, "20-29", Table1[[#This Row],[Age]]<40,"30-39",Table1[[#This Row],[Age]]<50,"40-49",Table1[[#This Row],[Age]]<60,"50-59",Table1[[#This Row],[Age]]<70, "60-69",Table1[[#This Row],[Age]]<80, "70-79",Table1[[#This Row],[Age]]<90,"80-89")} -> 20-29 | W78: TX | X78: Mechanic | Y78: Female | Z78: 80424 | AA78: White | AB78: Divorced | AC78: Fully Meets | AD78: 1
A79: 3501 | B79: Garrett | C79: Zimmerman | D79: 44073 | E79: 44803 | F79: =IF(Table1[[#This Row],[ExitDate]],QUOTIENT(Table1[[#This Row],[ExitDate]]-Table1[[#This Row],[StartDate]],365/12),"") -> 24 | G79: =IF(Table1[[#This Row],[ExitDate]], "Attrition", "Active") -> Attrition | H79: Area Sales Manager | I79: Destiny Hopkins | J79: garrett.zimmerman@bilearner.com | K79: PL | L79: Future Start | M79: Part-Time | N79: Zone A | O79: Part-Time | P79: Retirement | Q79: Worker medical commercial participant tough leg. | R79: Sales | S79: General - Con | T79: 21659 | U79: =YEARFRAC(Table1[[#This Row],[DOB]],TODAY()) -> 66.677778 | V79: {=_xlfn.IFS(Table1[[#This Row],[Age]] < 30, "20-29", Table1[[#This Row],[Age]]<40,"30-39",Table1[[#This Row],[Age]]<50,"40-49",Table1[[#This Row],[Age]]<60,"50-59",Table1[[#This Row],[Age]]<70, "60-69",Table1[[#This Row],[Age]]<80, "70-79",Table1[[#This Row],[Age]]<90,"80-89")} -> 60-69 | W79: TX | X79: Technician | Y79: Male | Z79: 6240 | AA79: Other | AB79: Widowed | AC79: Fully Meets | AD79: 4
A80: 3502 | B80: Eugene | C80: Marks | D80: 43739 | F80: =IF(Table1[[#This Row],[ExitDate]],QUOTIENT(Table1[[#This Row],[ExitDate]]-Table1[[#This Row],[StartDate]],365/12),"") | G80: =IF(Table1[[#This Row],[ExitDate]], "Attrition", "Active") -> Active | H80: Area Sales Manager | I80: Angela Morris | J80: eugene.marks@bilearner.com | K80: BPC | L80: Active | M80: Full-Time | N80: Zone C | O80: Temporary | P80: Unk | R80: Sales | S80: Splicing | T80: 27940 | U80: =YEARFRAC(Table1[[#This Row],[DOB]],TODAY()) -> 49.483333 | V80: {=_xlfn.IFS(Table1[[#This Row],[Age]] < 30, "20-29", Table1[[#This Row],[Age]]<40,"30-39",Table1[[#This Row],[Age]]<50,"40-49",Table1[[#This Row],[Age]]<60,"50-59",Table1[[#This Row],[Age]]<70, "60-69",Table1[[#This Row],[Age]]<80, "70-79",Table1[[#This Row],[Age]]<90,"80-89")} -> 40-49 | W80: TX | X80: Electrician | Y80: Male | Z80: 49914 | AA80: White | AB80: Married | AC80: Fully Meets | AD80: 1
A81: 3503 | B81: Geovanni | C81: Pugh | D81: 44581 | F81: =IF(Table1[[#This Row],[ExitDate]],QUOTIENT(Table1[[#This Row],[ExitDate]]-Table1[[#This Row],[StartDate]],365/12),"") | G81: =IF(Table1[[#This Row],[ExitDate]], "Attrition", "Active") -> Active | H81: Area Sales Manager | I81: Erica Franklin | J81: geovanni.pugh@bilearner.com | K81: CCDR | L81: Active | M81: Part-Time | N81: Zone A | O81: Temporary | P81: Unk | R81: Sales | S81: Project Management - Con | T81: 18836 | U81: =YEARFRAC(Table1[[#This Row],[DOB]],TODAY()) -> 74.405556 | V81: {=_xlfn.IFS(Table1[[#This Row],[Age]] < 30, "20-29", Table1[[#This Row],[Age]]<40,"30-39",Table1[[#This Row],[Age]]<50,"40-49",Table1[[#This Row],[Age]]<60,"50-59",Table1[[#This Row],[Age]]<70, "60-69",Table1[[#This Row],[Age]]<80, "70-79",Table1[[#This Row],[Age]]<90,"80-89")} -> 70-79 | W81: CO | X81: Manager | Y81: Male | Z81: 71319 | AA81: Other | AB81: Single | AC81: Fully Meets | AD81: 4
A82: 3504 | B82: Javon | C82: Kelley | D82: 44479 | F82: =IF(Table1[[#This Row],[ExitDate]],QUOTIENT(Table1[[#This Row],[ExitDate]]-Table1[[#This Row],[StartDate]],365/12),"") | G82: =IF(Table1[[#This Row],[ExitDate]], "Attrition", "Active") -> Active | H82: Area Sales Manager | I82: Gabriela Orr | J82: javon.kelley@bilearner.com | K82: SVG | L82: Active | M82: Full-Time | N82: Zone B | O82: Part-Time | P82: Unk | R82: Sales | S82: General - Con | T82: 29456 | U82: =YEARFRAC(Table1[[#This Row],[DOB]],TODAY()) -> 45.333333 | V82: {=_xlfn.IFS(Table1[[#This Row],[Age]] < 30, "20-29", Table1[[#This Row],[Age]]<40,"30-39",Table1[[#This Row],[Age]]<50,"40-49",Table1[[#This Row],[Age]]<60,"50-59",Table1[[#This Row],[Age]]<70, "60-69",Table1[[#This Row],[Age]]<80, "70-79",Table1[[#This Row],[Age]]<90,"80-89")} -> 40-49 | W82: CO | X82: Laborer | Y82: Male | Z82: 27992 | AA82: Hispanic | AB82: Married | AC82: Fully Meets | AD82: 2
A83: 3505 | B83: Amaya | C83: Hicks | D83: 44072 | F83: =IF(Table1[[#This Row],[ExitDate]],QUOTIENT(Table1[[#This Row],[ExitDate]]-Table1[[#This Row],[StartDate]],365/12),"") | G83: =IF(Table1[[#This Row],[ExitDate]], "Attrition", "Active") -> Active | H83: Area Sales Manager | I83: Michael Wilkins | J83: amaya.hicks@bilearner.com | K83: EW | L83: Active | M83: Contract | N83: Zone B | O83: Temporary | P83: Unk | R83: Sales | S83: Field Operations | T83: 15911 | U83: =YEARFRAC(Table1[[#This Row],[DOB]],TODAY()) -> 82.413889 | V83: {=_xlfn.IFS(Table1[[#This Row],[Age]] < 30, "20-29", Table1[[#This Row],[Age]]<40,"30-39",Table1[[#This Row],[Age]]<50,"40-49",Table1[[#This Row],[Age]]<60,"50-59",Table1[[#This Row],[Age]]<70, "60-69",Table1[[#This Row],[Age]]<80, "70-79",Table1[[#This Row],[Age]]<90,"80-89")} -> 80-89 | W83: IN | X83: Groundman | Y83: Male | Z83: 72324 | AA83: Hispanic | AB83: Widowed | AC83: Fully Meets | AD83: 1
A84: 3506 | B84: Laila | C84: Woodard | D84: 43704 | E84: 45056 | F84: =IF(Table1[[#This Row],[ExitDate]],QUOTIENT(Table1[[#This Row],[ExitDate]]-Table1[[#This Row],[StartDate]],365/12),"") -> 44 | G84: =IF(Table1[[#This Row],[ExitDate]], "Attrition", "Active") -> Attrition | H84: Area Sales Manager | I84: Jordan Vega | J84: laila.woodard@bilearner.com | K84: MSC | L84: Active | M84: Full-Time | N84: Zone B | O84: Temporary | P84: Voluntary | Q84: Fund nor half early miss follow. | R84: Sales | S84: Field Operations | T84: 32330 | U84: =YEARFRAC(Table1[[#This Row],[DOB]],TODAY()) -> 37.463889 | V84: {=_xlfn.IFS(Table1[[#This Row],[Age]] < 30, "20-29", Table1[[#This Row],[Age]]<40,"30-39",Table1[[#This Row],[Age]]<50,"40-49",Table1[[#This Row],[Age]]<60,"50-59",Table1[[#This Row],[Age]]<70, "60-69",Table1[[#This Row],[Age]]<80, "70-79",Table1[[#This Row],[Age]]<90,"80-89")} -> 30-39 | W84: IN | X84: Technician | Y84: Male | Z84: 38740 | AA84: Other | AB84: Married | AC84: Fully Meets | AD84: 2
A85: 3507 | B85: Ivan | C85: Huff | D85: 44252 | E85: 45023 | F85: =IF(Table1[[#This Row],[ExitDate]],QUOTIENT(Table1[[#This Row],[ExitDate]]-Table1[[#This Row],[StartDate]],365/12),"") -> 25 | G85: =IF(Table1[[#This Row],[ExitDate]], "Attrition", "Active") -> Attrition | H85: Area Sales Manager | I85: John Miller | J85: ivan.huff@bilearner.com | K85: TNS | L85: Active | M85: Full-Time | N85: Zone A | O85: Full-Time | P85: Retirement | Q85: Line later deal stand sometimes too mind. | R85: Sales | S85: Project Management - Con | T85: 26747 | U85: =YEARFRAC(Table1[[#This Row],[DOB]],TODAY()) -> 52.747222 | V85: {=_xlfn.IFS(Table1[[#This Row],[Age]] < 30, "20-29", Table1[[#This Row],[Age]]<40,"30-39",Table1[[#This Row],[Age]]<50,"40-49",Table1[[#This Row],[Age]]<60,"50-59",Table1[[#This Row],[Age]]<70, "60-69",Table1[[#This Row],[Age]]<80, "70-79",Table1[[#This Row],[Age]]<90,"80-89")} -> 50-59 | W85: CA | X85: Manager | Y85: Male | Z85: 9437 | AA85: White | AB85: Single | AC85: Fully Meets | AD85: 4
A86: 3508 | B86: Aidan | C86: Harding | D86: 44390 | F86: =IF(Table1[[#This Row],[ExitDate]],QUOTIENT(Table1[[#This Row],[ExitDate]]-Table1[[#This Row],[StartDate]],365/12),"") | G86: =IF(Table1[[#This Row],[ExitDate]], "Attrition", "Active") -> Active | H86: Area Sales Manager | I86: Trevor Adkins | J86: aidan.harding@bilearner.com | K86: CCDR | L86: Active | M86: Full-Time | N86: Zone B | O86: Part-Time | P86: Unk | R86: Sales | S86: Aerial | T86: 15487 | U86: =YEARFRAC(Table1[[#This Row],[DOB]],TODAY()) -> 83.575 | V86: {=_xlfn.IFS(Table1[[#This Row],[Age]] < 30, "20-29", Table1[[#This Row],[Age]]<40,"30-39",Table1[[#This Row],[Age]]<50,"40-49",Table1[[#This Row],[Age]]<60,"50-59",Table1[[#This Row],[Age]]<70, "60-69",Table1[[#This Row],[Age]]<80, "70-79",Table1[[#This Row],[Age]]<90,"80-89")} -> 80-89 | W86: OR | X86: Laborer | Y86: Male | Z86: 9385 | AA86: Asian | AB86: Single | AC86: Fully Meets | AD86: 5
A87: 3509 | B87: Cruz | C87: Boyer | D87: 44300 | F87: =IF(Table1[[#This Row],[ExitDate]],QUOTIENT(Table1[[#This Row],[ExitDate]]-Table1[[#This Row],[StartDate]],365/12),"") | G87: =IF(Table1[[#This Row],[ExitDate]], "Attrition", "Active") -> Active | H87: Area Sales Manager | I87: Marcus Hunt | J87: cruz.boyer@bilearner.com | K87: BPC | L87: Active | M87: Part-Time | N87: Zone C | O87: Full-Time | P87: Unk | R87: Sales | S87: General - Sga | T87: 28433 | U87: =YEARFRAC(Table1[[#This Row],[DOB]],TODAY()) -> 48.136111 | V87: {=_xlfn.IFS(Table1[[#This Row],[Age]] < 30, "20-29", Table1[[#This Row],[Age]]<40,"30-39",Table1[[#This Row],[Age]]<50,"40-49",Table1[[#This Row],[Age]]<60,"50-59",Table1[[#This Row],[Age]]<70, "60-69",Table1[[#This Row],[Age]]<80, "70-79",Table1[[#This Row],[Age]]<90,"80-89")} -> 40-49 | W87: KY | X87: Project Controls | Y87: Female | Z87: 75993 | AA87: Black | AB87: Married | AC87: Fully Meets | AD87: 2
A88: 3510 | B88: Raven | C88: Koch | D88: 43871 | F88: =IF(Table1[[#This Row],[ExitDate]],QUOTIENT(Table1[[#This Row],[ExitDate]]-Table1[[#This Row],[StartDate]],365/12),"") | G88: =IF(Table1[[#This Row],[ExitDate]], "Attrition", "Active") -> Active | H88: Area Sales Manager | I88: Jennifer King | J88: raven.koch@bilearner.com | K88: PYZ | L88: Active | M88: Part-Time | N88: Zone A | O88: Full-Time | P88: Unk | R88: Sales | S88: General - Con | T88: 20745 | U88: =YEARFRAC(Table1[[#This Row],[DOB]],TODAY()) -> 69.183333 | V88: {=_xlfn.IFS(Table1[[#This Row],[Age]] < 30, "20-29", Table1[[#This Row],[Age]]<40,"30-39",Table1[[#This Row],[Age]]<50,"40-49",Table1[[#This Row],[Age]]<60,"50-59",Table1[[#This Row],[Age]]<70, "60-69",Table1[[#This Row],[Age]]<80, "70-79",Table1[[#This Row],[Age]]<90,"80-89")} -> 60-69 | W88: KY | X88: Laborer | Y88: Female | Z88: 65329 | AA88: Hispanic | AB88: Married | AC88: Fully Meets | AD88: 2
A89: 3511 | B89: Karli | C89: Barker | D89: 44425 | E89: 44561 | F89: =IF(Table1[[#This Row],[ExitDate]],QUOTIENT(Table1[[#This Row],[ExitDate]]-Table1[[#This Row],[StartDate]],365/12),"") -> 4 | G89: =IF(Table1[[#This Row],[ExitDate]], "Attrition", "Active") -> Attrition | H89: Area Sales Manager | I89: Shawn Dudley | J89: karli.barker@bilearner.com | K89: WBL | L89: Active | M89: Part-Time | N89: Zone B | O89: Full-Time | P89: Resignation | Q89: Tell paper every. | R89: Sales | S89: Finance & Accounting | T89: 35479 | U89: =YEARFRAC(Table1[[#This Row],[DOB]],TODAY()) -> 28.847222 | V89: {=_xlfn.IFS(Table1[[#This Row],[Age]] < 30, "20-29", Table1[[#This Row],[Age]]<40,"30-39",Table1[[#This Row],[Age]]<50,"40-49",Table1[[#This Row],[Age]]<60,"50-59",Table1[[#This Row],[Age]]<70, "60-69",Table1[[#This Row],[Age]]<80, "70-79",Table1[[#This Row],[Age]]<90,"80-89")} -> 20-29 | W89: KY | X89: Director | Y89: Female | Z89: 41111 | AA89: Asian | AB89: Divorced | AC89: Fully Meets | AD89: 4
A90: 3512 | B90: Tyrone | C90: Sosa | D90: 45033 | E90: 45099 | F90: =IF(Table1[[#This Row],[ExitDate]],QUOTIENT(Table1[[#This Row],[ExitDate]]-Table1[[#This Row],[StartDate]],365/12),"") -> 2 | G90: =IF(Table1[[#This Row],[ExitDate]], "Attrition", "Active") -> Attrition | H90: Area Sales Manager | I90: Lindsay Chang | J90: tyrone.sosa@bilearner.com | K90: NEL | L90: Future Start | M90: Contract | N90: Zone C | O90: Temporary | P90: Voluntary | Q90: Why sport must page bad. | R90: Sales | S90: Yard (Material Handling) | T90: 35363 | U90: =YEARFRAC(Table1[[#This Row],[DOB]],TODAY()) -> 29.161111 | V90: {=_xlfn.IFS(Table1[[#This Row],[Age]] < 30, "20-29", Table1[[#This Row],[Age]]<40,"30-39",Table1[[#This Row],[Age]]<50,"40-49",Table1[[#This Row],[Age]]<60,"50-59",Table1[[#This Row],[Age]]<70, "60-69",Table1[[#This Row],[Age]]<80, "70-79",Table1[[#This Row],[Age]]<90,"80-89")} -> 20-29 | W90: TX | X90: Coordinator | Y90: Female | Z90: 58860 | AA90: Black | AB90: Single | AC90: Fully Meets | AD90: 2
A91: 3513 | B91: Damaris | C91: Cisneros | D91: 44806 | E91: 45070 | F91: =IF(Table1[[#This Row],[ExitDate]],QUOTIENT(Table1[[#This Row],[ExitDate]]-Table1[[#This Row],[StartDate]],365/12),"") -> 8 | G91: =IF(Table1[[#This Row],[ExitDate]], "Attrition", "Active") -> Attrition | H91: Area Sales Manager | I91: Sharon Ruiz | J91: damaris.cisneros@bilearner.com | K91: PL | L91: Future Start | M91: Contract | N91: Zone C | O91: Temporary | P91: Involuntary | Q91: Something sense information final building. | R91: Sales | S91: General - Con | T91: 21867 | U91: =YEARFRAC(Table1[[#This Row],[DOB]],TODAY()) -> 66.111111 | V91: {=_xlfn.IFS(Table1[[#This Row],[Age]] < 30, "20-29", Table1[[#This Row],[Age]]<40,"30-39",Table1[[#This Row],[Age]]<50,"40-49",Table1[[#This Row],[Age]]<60,"50-59",Table1[[#This Row],[Age]]<70, "60-69",Table1[[#This Row],[Age]]<80, "70-79",Table1[[#This Row],[Age]]<90,"80-89")} -> 60-69 | W91: TX | X91: Laborer | Y91: Male | Z91: 93051 | AA91: Other | AB91: Married | AC91: Fully Meets | AD91: 5
A92: 3514 | B92: Alexus | C92: Estes | D92: 43936 | F92: =IF(Table1[[#This Row],[ExitDate]],QUOTIENT(Table1[[#This Row],[ExitDate]]-Table1[[#This Row],[StartDate]],365/12),"") | G92: =IF(Table1[[#This Row],[ExitDate]], "Attrition", "Active") -> Active | H92: Area Sales Manager | I92: April Randolph | J92: alexus.estes@bilearner.com | K92: BPC | L92: Active | M92: Full-Time | N92: Zone B | O92: Part-Time | P92: Unk | R92: Sales | S92: Wireline Construction | T92: 21188 | U92: =YEARFRAC(Table1[[#This Row],[DOB]],TODAY()) -> 67.972222 | V92: {=_xlfn.IFS(Table1[[#This Row],[Age]] < 30, "20-29", Table1[[#This Row],[Age]]<40,"30-39",Table1[[#This Row],[Age]]<50,"40-49",Table1[[#This Row],[Age]]<60,"50-59",Table1[[#This Row],[Age]]<70, "60-69",Table1[[#This Row],[Age]]<80, "70-79",Table1[[#This Row],[Age]]<90,"80-89")} -> 60-69 | W92: TX | X92: Manager | Y92: Male | Z92: 17419 | AA92: Asian | AB92: Married | AC92: Fully Meets | AD92: 1
A93: 3515 | B93: Kinsley | C93: Flowers | D93: 44629 | E93: 44905 | F93: =IF(Table1[[#This Row],[ExitDate]],QUOTIENT(Table1[[#This Row],[ExitDate]]-Table1[[#This Row],[StartDate]],365/12),"") -> 9 | G93: =IF(Table1[[#This Row],[ExitDate]], "Attrition", "Active") -> Attrition | H93: Area Sales Manager | I93: Mary Reilly | J93: kinsley.flowers@bilearner.com | K93: CCDR | L93: Future Start | M93: Part-Time | N93: Zone A | O93: Part-Time | P93: Retirement | Q93: School see rest firm I. | R93: Sales | S93: Finance & Accounting | T93: 35549 | U93: =YEARFRAC(Table1[[#This Row],[DOB]],TODAY()) -> 28.65 | V93: {=_xlfn.IFS(Table1[[#This Row],[Age]] < 30, "20-29", Table1[[#This Row],[Age]]<40,"30-39",Table1[[#This Row],[Age]]<50,"40-49",Table1[[#This Row],[Age]]<60,"50-59",Table1[[#This Row],[Age]]<70, "60-69",Table1[[#This Row],[Age]]<80, "70-79",Table1[[#This Row],[Age]]<90,"80-89")} -> 20-29 | W93: CO | X93: Controller | Y93: Male | Z93: 59593 | AA93: White | AB93: Single | AC93: Fully Meets | AD93: 4
A94: 3516 | B94: Deborah | C94: Love | D94: 44658 | E94: 44948 | F94: =IF(Table1[[#This Row],[ExitDate]],QUOTIENT(Table1[[#This Row],[ExitDate]]-Table1[[#This Row],[StartDate]],365/12),"") -> 9 | G94: =IF(Table1[[#This Row],[ExitDate]], "Attrition", "Active") -> Attrition | H94: Area Sales Manager | I94: Eric Goodman | J94: deborah.love@bilearner.com | K94: SVG | L94: Active | M94: Contract | N94: Zone B | O94: Part-Time | P94: Retirement | Q94: Source doctor rock group this. | R94: Sales | S94: Project Management - Con | T94: 32319 | U94: =YEARFRAC(Table1[[#This Row],[DOB]],TODAY()) -> 37.494444 | V94: {=_xlfn.IFS(Table1[[#This Row],[Age]] < 30, "20-29", Table1[[#This Row],[Age]]<40,"30-39",Table1[[#This Row],[Age]]<50,"40-49",Table1[[#This Row],[Age]]<60,"50-59",Table1[[#This Row],[Age]]<70, "60-69",Table1[[#This Row],[Age]]<80, "70-79",Table1[[#This Row],[Age]]<90,"80-89")} -> 30-39 | W94: CO | X94: Coordinator | Y94: Male | Z94: 96350 | AA94: Asian | AB94: Divorced | AC94: Fully Meets | AD94: 5
A95: 3517 | B95: Milagros | C95: Francis | D95: 43880 | F95: =IF(Table1[[#This Row],[ExitDate]],QUOTIENT(Table1[[#This Row],[ExitDate]]-Table1[[#This Row],[StartDate]],365/12),"") | G95: =IF(Table1[[#This Row],[ExitDate]], "Attrition", "Active") -> Active | H95: Area Sales Manager | I95: Caleb Schneider | J95: milagros.francis@bilearner.com | K95: EW | L95: Active | M95: Part-Time | N95: Zone A | O95: Part-Time | P95: Unk | R95: Sales | S95: Splicing | T95: 15345 | U95: =YEARFRAC(Table1[[#This Row],[DOB]],TODAY()) -> 83.969444 | V95: {=_xlfn.IFS(Table1[[#This Row],[Age]] < 30, "20-29", Table1[[#This Row],[Age]]<40,"30-39",Table1[[#This Row],[Age]]<50,"40-49",Table1[[#This Row],[Age]]<60,"50-59",Table1[[#This Row],[Age]]<70, "60-69",Table1[[#This Row],[Age]]<80, "70-79",Table1[[#This Row],[Age]]<90,"80-89")} -> 80-89 | W95: IN | X95: Splicer | Y95: Male | Z95: 44469 | AA95: Hispanic | AB95: Widowed | AC95: Fully Meets | AD95: 4
A96: 3518 | B96: Roberto | C96: Michael | D96: 44296 | E96: 44746 | F96: =IF(Table1[[#This Row],[ExitDate]],QUOTIENT(Table1[[#This Row],[ExitDate]]-Table1[[#This Row],[StartDate]],365/12),"") -> 14 | G96: =IF(Table1[[#This Row],[ExitDate]], "Attrition", "Active") -> Attrition | H96: Area Sales Manager | I96: Cheryl Henry | J96: roberto.michael@bilearner.com | K96: MSC | L96: Active | M96: Contract | N96: Zone B | O96: Part-Time | P96: Involuntary | Q96: Little imagine career he produce program. | R96: Sales | S96: General - Eng | T96: 25347 | U96: =YEARFRAC(Table1[[#This Row],[DOB]],TODAY()) -> 56.580556 | V96: {=_xlfn.IFS(Table1[[#This Row],[Age]] < 30, "20-29", Table1[[#This Row],[Age]]<40,"30-39",Table1[[#This Row],[Age]]<50,"40-49",Table1[[#This Row],[Age]]<60,"50-59",Table1[[#This Row],[Age]]<70, "60-69",Table1[[#This Row],[Age]]<80, "70-79",Table1[[#This Row],[Age]]<90,"80-89")} -> 50-59 | W96: CA | X96: Coordinator | Y96: Female | Z96: 13249 | AA96: Hispanic | AB96: Married | AC96: Fully Meets | AD96: 2
A97: 3519 | B97: Elaine | C97: Ewing | D97: 44549 | E97: 44622 | F97: =IF(Table1[[#This Row],[ExitDate]],QUOTIENT(Table1[[#This Row],[ExitDate]]-Table1[[#This Row],[StartDate]],365/12),"") -> 2 | G97: =IF(Table1[[#This Row],[ExitDate]], "Attrition", "Active") -> Attrition | H97: Area Sales Manager | I97: Dan Hernandez | J97: elaine.ewing@bilearner.com | K97: TNS | L97: Active | M97: Part-Time | N97: Zone C | O97: Temporary | P97: Resignation | Q97: Your very trip successful memory to while out. | R97: Sales | S97: Aerial | T97: 18715 | U97: =YEARFRAC(Table1[[#This Row],[DOB]],TODAY()) -> 74.736111 | V97: {=_xlfn.IFS(Table1[[#This Row],[Age]] < 30, "20-29", Table1[[#This Row],[Age]]<40,"30-39",Table1[[#This Row],[Age]]<50,"40-49",Table1[[#This Row],[Age]]<60,"50-59",Table1[[#This Row],[Age]]<70, "60-69",Table1[[#This Row],[Age]]<80, "70-79",Table1[[#This Row],[Age]]<90,"80-89")} -> 70-79 | W97: CA | X97: Groundman | Y97: Male | Z97: 17123 | AA97: Hispanic | AB97: Widowed | AC97: Fully Meets | AD97: 2
A98: 3520 | B98: Caiden | C98: Munoz | D98: 44178 | E98: 44939 | F98: =IF(Table1[[#This Row],[ExitDate]],QUOTIENT(Table1[[#This Row],[ExitDate]]-Table1[[#This Row],[StartDate]],365/12),"") -> 25 | G98: =IF(Table1[[#This Row],[ExitDate]], "Attrition", "Active") -> Attrition | H98: Area Sales Manager | I98: Teresa Daniel | J98: caiden.munoz@bilearner.com | K98: TNS | L98: Active | M98: Full-Time | N98: Zone C | O98: Temporary | P98: Involuntary | Q98: Red some option. | R98: Sales | S98: Project Management - Con | T98: 23071 | U98: =YEARFRAC(Table1[[#This Row],[DOB]],TODAY()) -> 62.811111 | V98: {=_xlfn.IFS(Table1[[#This Row],[Age]] < 30, "20-29", Table1[[#This Row],[Age]]<40,"30-39",Table1[[#This Row],[Age]]<50,"40-49",Table1[[#This Row],[Age]]<60,"50-59",Table1[[#This Row],[Age]]<70, "60-69",Table1[[#This Row],[Age]]<80, "70-79",Table1[[#This Row],[Age]]<90,"80-89")} -> 60-69 | W98: ND | X98: Manager | Y98: Female | Z98: 18983 | AA98: Black | AB98: Divorced | AC98: Fully Meets | AD98: 1
A99: 3521 | B99: Jocelyn | C99: Bradford | D99: 43522 | F99: =IF(Table1[[#This Row],[ExitDate]],QUOTIENT(Table1[[#This Row],[ExitDate]]-Table1[[#This Row],[StartDate]],365/12),"") | G99: =IF(Table1[[#This Row],[ExitDate]], "Attrition", "Active") -> Active | H99: Area Sales Manager | I99: Melissa Decker | J99: jocelyn.bradford@bilearner.com | K99: WBL | L99: Active | M99: Contract | N99: Zone C | O99: Part-Time | P99: Unk | R99: Sales | S99: General - Con | T99: 18004 | U99: =YEARFRAC(Table1[[#This Row],[DOB]],TODAY()) -> 76.686111 | V99: {=_xlfn.IFS(Table1[[#This Row],[Age]] < 30, "20-29", Table1[[#This Row],[Age]]<40,"30-39",Table1[[#This Row],[Age]]<50,"40-49",Table1[[#This Row],[Age]]<60,"50-59",Table1[[#This Row],[Age]]<70, "60-69",Table1[[#This Row],[Age]]<80, "70-79",Table1[[#This Row],[Age]]<90,"80-89")} -> 70-79 | W99: KY | X99: Electrician | Y99: Female | Z99: 51795 | AA99: Asian | AB99: Divorced | AC99: Fully Meets | AD99: 4
A100: 3522 | B100: Marques | C100: Armstrong | D100: 43892 | F100: =IF(Table1[[#This Row],[ExitDate]],QUOTIENT(Table1[[#This Row],[ExitDate]]-Table1[[#This Row],[StartDate]],365/12),"") | G100: =IF(Table1[[#This Row],[ExitDate]], "Attrition", "Active") -> Active | H100: Area Sales Manager | I100: Michael Nguyen | J100: marques.armstrong@bilearner.com | K100: BPC | L100: Active | M100: Full-Time | N100: Zone C | O100: Part-Time | P100: Unk | R100: Sales | S100: Splicing | T100: 30601 | U100: =YEARFRAC(Table1[[#This Row],[DOB]],TODAY()) -> 42.197222 | V100: {=_xlfn.IFS(Table1[[#This Row],[Age]] < 30, "20-29", Table1[[#This Row],[Age]]<40,"30-39",Table1[[#This Row],[Age]]<50,"40-49",Table1[[#This Row],[Age]]<60,"50-59",Table1[[#This Row],[Age]]<70, "60-69",Table1[[#This Row],[Age]]<80, "70-79",Table1[[#This Row],[Age]]<90,"80-89")} -> 40-49 | W100: KY | X100: Splicer | Y100: Female | Z100: 34369 | AA100: Other | AB100: Single | AC100: Fully Meets | AD100: 1
A101: 3523 | B101: Rohan | C101: Chapman | D101: 44372 | E101: 44798 | F101: =IF(Table1[[#This Row],[ExitDate]],QUOTIENT(Table1[[#This Row],[ExitDate]]-Table1[[#This Row],[StartDate]],365/12),"") -> 14 | G101: =IF(Table1[[#This Row],[ExitDate]], "Attrition", "Active") -> Attrition | H101: Area Sales Manager | I101: Tony Mcconnell | J101: rohan.chapman@bilearner.com | K101: CCDR | L101: Active | M101: Full-Time | N101: Zone A | O101: Temporary | P101: Resignation | Q101: Theory grow future week house. | R101: Sales | S101: General - Con | T101: 28843 | U101: =YEARFRAC(Table1[[#This Row],[DOB]],TODAY()) -> 47.011111 | V101: {=_xlfn.IFS(Table1[[#This Row],[Age]] < 30, "20-29", Table1[[#This Row],[Age]]<40,"30-39",Table1[[#This Row],[Age]]<50,"40-49",Table1[[#This Row],[Age]]<60,"50-59",Table1[[#This Row],[Age]]<70, "60-69",Table1[[#This Row],[Age]]<80, "70-79",Table1[[#This Row],[Age]]<90,"80-89")} -> 40-49 | W101: KY | X101: Laborer | Y101: Female | Z101: 23092 | AA101: Other | AB101: Single | AC101: Fully Meets | AD101: 2
A102: 3524 | B102: Emmanuel | C102: Franklin | D102: 44403 | E102: 44685 | F102: =IF(Table1[[#This Row],[ExitDate]],QUOTIENT(Table1[[#This Row],[ExitDate]]-Table1[[#This Row],[StartDate]],365/12),"") -> 9 | G102: =IF(Table1[[#This Row],[ExitDate]], "Attrition", "Active") -> Attrition | H102: Area Sales Manager | I102: Adam Gibson | J102: emmanuel.franklin@bilearner.com | K102: EW | L102: Future Start | M102: Contract | N102: Zone B | O102: Full-Time | P102: Resignation | Q102: Inside week also so. | R102: Sales | S102: Field Operations | T102: 36475 | U102: =YEARFRAC(Table1[[#This Row],[DOB]],TODAY()) -> 26.116667 | V102: {=_xlfn.IFS(Table1[[#This Row],[Age]] < 30, "20-29", Table1[[#This Row],[Age]]<40,"30-39",Table1[[#This Row],[Age]]<50,"40-49",Table1[[#This Row],[Age]]<60,"50-59",Table1[[#This Row],[Age]]<70, "60-69",Table1[[#This Row],[Age]]<80, "70-79",Table1[[#This Row],[Age]]<90,"80-89")} -> 20-29 | W102: TX | X102: Laborer | Y102: Male | Z102: 6074 | AA102: Asian | AB102: Divorced | AC102: Fully Meets | AD102: 2
A103: 3525 | B103: Clayton | C103: Mccormick | D103: 44745 | E103: 44936 | F103: =IF(Table1[[#This Row],[ExitDate]],QUOTIENT(Table1[[#This Row],[ExitDate]]-Table1[[#This Row],[StartDate]],365/12),"") -> 6 | G103: =IF(Table1[[#This Row],[ExitDate]], "Attrition", "Active") -> Attrition | H103: Area Sales Manager | I103: Stephanie Duke | J103: clayton.mccormick@bilearner.com | K103: MSC | L103: Future Start | M103: Contract | N103: Zone B | O103: Temporary | P103: Retirement | Q103: Surface vote old picture. | R103: Sales | S103: General - Con | T103: 24501 | U103: =YEARFRAC(Table1[[#This Row],[DOB]],TODAY()) -> 58.9 | V103: {=_xlfn.IFS(Table1[[#This Row],[Age]] < 30, "20-29", Table1[[#This Row],[Age]]<40,"30-39",Table1[[#This Row],[Age]]<50,"40-49",Table1[[#This Row],[Age]]<60,"50-59",Table1[[#This Row],[Age]]<70, "60-69",Table1[[#This Row],[Age]]<80, "70-79",Table1[[#This Row],[Age]]<90,"80-89")} -> 50-59 | W103: TX | X103: Foreman | Y103: Male | Z103: 72264 | AA103: Hispanic | AB103: Single | AC103: Fully Meets | AD103: 2
...

Sheet Sheet2
A3: Count of EmpID | B3: Column Labels | F3: Row Labels | G3: Average of Current Employee Rating
A4: Row Labels | B4: Female | C4: Male | D4: Grand Total | F4: Admin Offices | G4: 2.9583333
A5: Admin Offices | B5: 28 | C5: 20 | D5: 48 | F5: Executive Office | G5: 2.8421053
A6: Executive Office | B6: 1 | C6: 18 | D6: 19 | F6: IT/IS | G6: 2.9866071
A7: IT/IS | B7: 107 | C7: 117 | D7: 224 | F7: Production | G7: 2.9930966
A8: Sales | B8: 53 | C8: 111 | D8: 164 | F8: Sales | G8: 2.8658537
A9: Software Engineering | B9: 28 | C9: 36 | D9: 64 | F9: Software Engineering | G9: 3.015625
A10: Production | B10: 648 | C10: 366 | D10: 1014 | F10: Grand Total | G10: 2.9765166
A11: Grand Total | B11: 865 | C11: 668 | D11: 1533
A13: Row Labels | B13: Average of Age | F13: Count of EmpID | G13: Column Labels
A14: Software Engineering | B14: 50.936979 | F14: Row Labels | G14: Full-Time | H14: Part-Time | I14: Temporary | J14: Grand Total
A15: Sales | B15: 53.316684 | F15: Executive Office | G15: 6 | H15: 7 | I15: 6 | J15: 19
A16: Production | B16: 54.45549 | F16: Admin Offices | G16: 14 | H16: 19 | I16: 15 | J16: 48
A17: IT/IS | B17: 54.661 | F17: Software Engineering | G17: 16 | H17: 30 | I17: 18 | J17: 64
A18: Executive Office | B18: 56.061842 | F18: Sales | G18: 56 | H18: 43 | I18: 65 | J18: 164
A19: Admin Offices | B19: 57.468519 | F19: IT/IS | G19: 76 | H19: 60 | I19: 88 | J19: 224
A20: Grand Total | B20: 54.331048 | F20: Production | G20: 336 | H20: 318 | I20: 360 | J20: 1014
F21: Grand Total | G21: 504 | H21: 477 | I21: 552 | J21: 1533
A22: Row Labels | B22: Average of Tenure
A23: Software Engineering | B23: 13.5
A24: Sales | B24: 14.664634
A25: Production | B25: 15.672584
A26: Admin Offices | B26: 15.729167
A27: IT/IS | B27: 16.09375
A28: Executive Office | B28: 16.421053
A29: Grand Total | B29: 15.546641

Sheet Sheet5
A3: Average of Current Employee Rating | B3: Column Labels | G3: Row Labels | H3: Average of Tenure | J3: Row Labels | K3: Average of Current Employee Rating
A4: Row Labels | B4: Zone A | C4: Zone B | D4: Zone C | E4: Grand Total | G4: 20-29 | H4: 15.552632 | J4: Full-Time | K4: 2.9424603
A5: Exceeds | B5: 2.7826087 | C5: 2.9402985 | D5: 3.0909091 | E5: 2.9267016 | G5: 30-39 | H5: 15.157509 | J5: Part-Time | K5: 3.033543
A6: Fully Meets | B6: 2.9976077 | C6: 2.9285714 | D6: 2.9920635 | E6: 2.9725458 | G6: 40-49 | H6: 16.058333 | J6: Temporary | K6: 2.9583333
A7: Needs Improvement | B7: 3.15625 | C7: 3.1481481 | D7: 3.09375 | E7: 3.1318681 | G7: 50-59 | H7: 15.599099 | J7: Grand Total | K7: 2.9765166
A8: PIP | B8: 3.2941176 | C8: 3.1578947 | D8: 2.3076923 | E8: 2.9795918 | G8: 60-69 | H8: 13.996416
A9: Grand Total | B9: 2.988806 | C9: 2.9499037 | D9: 2.9916318 | E9: 2.9765166 | G9: 70-79 | H9: 17.343874
G10: 80-89 | H10: 15.096491
B11: Row Labels | C11: Average of Tenure | G11: Grand Total | H11: 15.546641
B12: Involuntary | C12: 16.456186
B13: Resignation | C13: 15.626316 | G13: Row Labels | H13: Average of Tenure
B14: Retirement | C14: 15.114058 | G14: Exceeds | H14: 17.628272
B15: Voluntary | C15: 14.979381 | G15: Fully Meets | H15: 15.168885
B16: Grand Total | C16: 15.546641 | G16: Needs Improvement | H16: 14.43956
G17: PIP | H17: 18.755102
B18: Row Labels | C18: Average of Tenure | G18: Grand Total | H18: 15.546641
B19: Full-Time | C19: 16.406746
B20: Part-Time | C20: 15.30608
B21: Temporary | C21: 14.969203
B22: Grand Total | C22: 15.546641

Sheet Sheet3
A3: EmpID | B3: FirstName | C3: LastName | D3: StartDate | E3: ExitDate | F3: Tenure | G3: Status | H3: Title | I3: Supervisor | J3: ADEmail | K3: BusinessUnit | L3: EmployeeStatus | M3: EmployeeType | N3: PayZone | O3: EmployeeClassificationType | P3: TerminationType | Q3: TerminationDescription | R3: DepartmentType | S3: Division | T3: DOB | U3: Age | V3: Age Group | W3: State | X3: JobFunctionDescription | Y3: GenderCode | Z3: LocationCode | AA3: RaceDesc | AB3: MaritalDesc | AC3: Performance Score | AD3: Current Employee Rating | AE3: StateName
A4: 3433 | B4: Latia | C4: Costa | D4: 44657 | E4: 45110 | F4: 14 | G4: Attrition | H4: Area Sales Manager | I4: Jacob Braun | J4: latia.costa@bilearner.com | K4: WBL | L4: Active | M4: Full-Time | N4: Zone B | O4: Temporary | P4: Involuntary | Q4: Me see picture nature degree benefit. | R4: Sales | S4: General - Eng | T4: 15523 | U4: 83.469444 | V4: 80-89 | W4: CA | X4: Technician | Y4: Female | Z4: 90007 | AA4: Hispanic | AB4: Divorced | AC4: Exceeds | AD4: 4 | AE4: =VLOOKUP(W4,Sheet4!$A$4:$B$53,2,FALSE) -> 0
A5: 3434 | B5: Sharlene | C5: Terry | D5: 44141 | E5: 44955 | F5: 26 | G5: Attrition | H5: Area Sales Manager | I5: Tracy Marquez | J5: sharlene.terry@bilearner.com | K5: CCDR | L5: Active | M5: Contract | N5: Zone C | O5: Full-Time | P5: Involuntary | Q5: Blue community type skill story. | R5: Sales | S5: Engineers | T5: 20886 | U5: 68.786111 | V5: 60-69 | W5: OR | X5: Engineer | Y5: Female | Z5: 97756 | AA5: White | AB5: Divorced | AC5: Fully Meets | AD5: 2 | AE5: =VLOOKUP(W5,Sheet4!$A$4:$B$53,2,FALSE) -> 0
A6: 3436 | B6: Joseph | C6: Martins | D6: 44582 | E6: 45106 | F6: 17 | G6: Attrition | H6: Area Sales Manager | I6: George Jenkins | J6: joseph.martins@bilearner.com | K6: BPC | L6: Active | M6: Part-Time | N6: Zone B | O6: Temporary | P6: Resignation | Q6: Summer personal bag. | R6: Sales | S6: Engineers | T6: 18213 | U6: 76.108333 | V6: 70-79 | W6: TX | X6: Engineer | Y6: Male | Z6: 78207 | AA6: Asian | AB6: Widowed | AC6: Fully Meets | AD6: 5 | AE6: =VLOOKUP(W6,Sheet4!$A$4:$B$53,2,FALSE) -> 0
A7: 3438 | B7: Dheepa | C7: Nguyen | D7: 43322 | E7: 43773 | F7: 14 | G7: Attrition | H7: Area Sales Manager | I7: Brian Miller | J7: dheepa.nguyen@bilearner.com | K7: MSC | L7: Active | M7: Full-Time | N7: Zone C | O7: Temporary | P7: Retirement | Q7: Alone once than. More condition pay far. | R7: Sales | S7: General - Con | T7: 17629 | U7: 77.705556 | V7: 70-79 | W7: GA | X7: Technician | Y7: Female | Z7: 30428 | AA7: Asian | AB7: Married | AC7: Fully Meets | AD7: 3 | AE7: =VLOOKUP(W7,Sheet4!$A$4:$B$53,2,FALSE) -> 0
A8: 3439 | B8: Bartholemew | C8: Khemmich | D8: 44706 | E8: 44892 | F8: 6 | G8: Attrition | H8: Area Sales Manager | I8: Charles Parks | J8: bartholemew.khemmich@bilearner.com | K8: EW | L8: Active | M8: Full-Time | N8: Zone A | O8: Temporary | P8: Involuntary | Q8: Foot in theory minute recognize test. | R8: Sales | S8: Splicing | T8: 29914 | U8: 44.072222 | V8: 40-49 | W8: CO | X8: Splicer | Y8: Male | Z8: 80820 | AA8: Other | AB8: Single | AC8: Fully Meets | AD8: 3 | AE8: =VLOOKUP(W8,Sheet4!$A$4:$B$53,2,FALSE) -> 0
A9: 3440 | B9: Xana | C9: Potts | D9: 43804 | E9: 44974 | F9: 38 | G9: Attrition | H9: Area Sales Manager | I9: Gregory Walker | J9: xana.potts@bilearner.com | K9: CCDR | L9: Active | M9: Contract | N9: Zone A | O9: Full-Time | P9: Resignation | Q9: Degree wish science when thing week old. | R9: Sales | S9: Finance & Accounting | T9: 18938 | U9: 74.122222 | V9: 70-79 | W9: KY | X9: Controller | Y9: Female | Z9: 40220 | AA9: White | AB9: Divorced | AC9: Fully Meets | AD9: 3 | AE9: =VLOOKUP(W9,Sheet4!$A$4:$B$53,2,FALSE) -> 0
A10: 3442 | B10: Kaylah | C10: Moon | D10: 43655 | E10: 44728 | F10: 35 | G10: Attrition | H10: Area Sales Manager | I10: Ashley Scott | J10: kaylah.moon@bilearner.com | K10: PYZ | L10: Active | M10: Full-Time | N10: Zone A | O10: Full-Time | P10: Retirement | Q10: Fear particular method stage. | R10: IT/IS | S10: Field Operations | T10: 19322 | U10: 73.072222 | V10: 70-79 | W10: MA | X10: Laborer | Y10: Male | Z10: 2810 | AA10: Black | AB10: Single | AC10: Exceeds | AD10: 2 | AE10: =VLOOKUP(W10,Sheet4!$A$4:$B$53,2,FALSE) -> 0
A11: 3443 | B11: Kristen | C11: Tate | D11: 44291 | E11: 45058 | F11: 25 | G11: Attrition | H11: Area Sales Manager | I11: Lauren Jones | J11: kristen.tate@bilearner.com | K11: WBL | L11: Active | M11: Full-Time | N11: Zone C | O11: Part-Time | P11: Voluntary | Q11: Wall body wonder successful. | R11: IT/IS | S11: Project Management - Con | T11: 34432 | U11: 31.7 | V11: 30-39 | W11: KY | X11: Coordinator | Y11: Male | Z11: 2621 | AA11: Asian | AB11: Widowed | AC11: Fully Meets | AD11: 3 | AE11: =VLOOKUP(W11,Sheet4!$A$4:$B$53,2,FALSE) -> 0
A12: 3444 | B12: Bobby | C12: Rodgers | D12: 44528 | E12: 44596 | F12: 2 | G12: Attrition | H12: Area Sales Manager | I12: Matthew Jackson | J12: bobby.rodgers@bilearner.com | K12: NEL | L12: Active | M12: Contract | N12: Zone A | O12: Part-Time | P12: Voluntary | Q12: Visit foot nearly radio treatment. | R12: Sales | S12: Engineers | T12: 30635 | U12: 42.097222 | V12: 40-49 | W12: KY | X12: Director | Y12: Male | Z12: 44553 | AA12: Other | AB12: Widowed | AC12: Fully Meets | AD12: 3 | AE12: =VLOOKUP(W12,Sheet4!$A$4:$B$53,2,FALSE) -> 0
A13: 3447 | B13: Mariela | C13: Schultz | D13: 43977 | E13: 45095 | F13: 36 | G13: Attrition | H13: Area Sales Manager | I13: Michelle Evans MD | J13: mariela.schultz@bilearner.com | K13: CCDR | L13: Future Start | M13: Part-Time | N13: Zone C | O13: Part-Time | P13: Involuntary | Q13: Unit pass office southern break one. | R13: Sales | S13: General - Con | T13: 23424 | U13: 61.841667 | V13: 60-69 | W13: TX | X13: Technician | Y13: Female | Z13: 43481 | AA13: Asian | AB13: Widowed | AC13: Fully Meets | AD13: 3 | AE13: =VLOOKUP(W13,Sheet4!$A$4:$B$53,2,FALSE) -> 0
A14: 3448 | B14: Angela | C14: Molina | D14: 43739 | E14: 44141 | F14: 13 | G14: Attrition | H14: Area Sales Manager | I14: Patricia Cook | J14: angela.molina@bilearner.com | K14: SVG | L14: Future Start | M14: Full-Time | N14: Zone A | O14: Temporary | P14: Retirement | Q14: List class mind. | R14: Sales | S14: Engineers | T14: 21317 | U14: 67.605556 | V14: 60-69 | W14: TX | X14: Specialist | Y14: Male | Z14: 50705 | AA14: Asian | AB14: Widowed | AC14: Fully Meets | AD14: 3 | AE14: =VLOOKUP(W14,Sheet4!$A$4:$B$53,2,FALSE) -> 0
A15: 3449 | B15: Gerald | C15: Preston | D15: 45056 | E15: 45073 | F15: 0 | G15: Attrition | H15: Area Sales Manager | I15: Ashley Reeves | J15: gerald.preston@bilearner.com | K15: EW | L15: Future Start | M15: Contract | N15: Zone B | O15: Temporary | P15: Involuntary | Q15: Price third parent evening. | R15: Sales | S15: General - Eng | T15: 33865 | U15: 33.255556 | V15: 30-39 | W15: CO | X15: Technician | Y15: Male | Z15: 5168 | AA15: Black | AB15: Single | AC15: Fully Meets | AD15: 5 | AE15: =VLOOKUP(W15,Sheet4!$A$4:$B$53,2,FALSE) -> 0
... A308: 1006 | B308: Colby | C308: Andreola | D308: 44423 | E308: 44520 | F308: 3 | G308: Attrition | H308: Software Engineer | I308: Beth Johnson | J308: colby.andreola@bilearner.com | K308: MSC | L308: Active | M308: Full-Time | N308: Zone C | O308: Part-Time | P308: Resignation | Q308: Throughout yet in serious here wish. | R308: Software Engineering | S308: Engineers | T308: 21600 | U308: 66.836111 | V308: 60-69 | W308: MA | X308: Administrative | Y308: Female | Z308: 2110 | AA308: White | AB308: Widowed | AC308: Fully Meets | AD308: 3 | AE308: =VLOOKUP(W308,Sheet4!$A$4:$B$53,2,FALSE) -> 0
A309: 1007 | B309: Edward | C309: TRUE | D309: 44129 | E309: 44465 | F309: 11 | G309: Attrition | H309: Software Engineer | I309: Raymond Adams | J309: edward.true@bilearner.com | K309: SVG | L309: Voluntarily Terminated | M309: Part-Time | N309: Zone A | O309: Part-Time | P309: Involuntary | Q309: Recently however meeting economic. | R309: Software Engineering | S309: General - Con | T309: 36603 | U309: 25.755556 | V309: 20-29 | W309: MA | X309: Lineman | Y309: Male | Z309: 2451 | AA309: Black | AB309: Widowed | AC309: Fully Meets | AD309: 3 | AE309: =VLOOKUP(W309,Sheet4!$A$4:$B$53,2,FALSE) -> 0
A310: 1008 | B310: Judith | C310: Carabbio | D310: 43705 | E310: 43955 | F310: 8 | G310: Attrition | H310: Software Engineer | I310: Jessica Rhodes | J310: judith.carabbio@bilearner.com | K310: BPC | L310: Active | M310: Contract | N310: Zone B | O310: Temporary | P310: Voluntary | Q310: Instead story skill financial who. | R310: Software Engineering | S310: General - Con | T310: 29941 | U310: 43.997222 | V310: 40-49 | W310: MA | X310: Foreman | Y310: Female | Z310: 2132 | AA310: Hispanic | AB310: Married | AC310: Fully Meets | AD310: 3 | AE310: =VLOOKUP(W310,Sheet4!$A$4:$B$53,2,FALSE) -> 0
A311: 1009 | B311: Adell | C311: Saada | D311: 43629 | E311: 44938 | F311: 43 | G311: Attrition | H311: Software Engineer | I311: Steven Tran | J311: adell.saada@bilearner.com | K311: NEL | L311: Active | M311: Part-Time | N311: Zone C | O311: Temporary | P311: Retirement | Q311: Exactly vote including easy. | R311: Software Engineering | S311: General - Con | T311: 31837 | U311: 38.802778 | V311: 30-39 | W311: MA | X311: Model Assistant | Y311: Female | Z311: 2132 | AA311: Other | AB311: Single | AC311: Fully Meets | AD311: 3 | AE311: =VLOOKUP(W311,Sheet4!$A$4:$B$53,2,FALSE) -> 0
A312: 1010 | B312: Kamari | C312: Hunter | D312: 44208 | E312: 44638 | F312: 14 | G312: Attrition | H312: Software Engineer | I312: Kristen Collier | J312: kamari.hunter@bilearner.com | K312: EW | L312: Voluntarily Terminated | M312: Part-Time | N312: Zone C | O312: Temporary | P312: Voluntary | Q312: West note present Mr woman family. | R312: Software Engineering | S312: Field Operations | T312: 33898 | U312: 33.163889 | V312: 30-39 | W312: MA | X312: Supervisor | Y312: Male | Z312: 12889 | AA312: Hispanic | AB312: Divorced | AC312: Fully Meets | AD312: 3 | AE312: =VLOOKUP(W312,Sheet4!$A$4:$B$53,2,FALSE) -> 0
A313: 1011 | B313: Sarah | C313: Malone | D313: 44599 | E313: 44969 | F313: 12 | G313: Attrition | H313: Software Engineer | I313: David Lopez | J313: sarah.malone@bilearner.com | K313: MSC | L313: Voluntarily Terminated | M313: Contract | N313: Zone A | O313: Temporary | P313: Resignation | Q313: Professor situation they bag interest there. | R313: Software Engineering | S313: General - Con | T313: 17585 | U313: 77.827778 | V313: 70-79 | W313: MA | X313: Foreman | Y313: Male | Z313: 21340 | AA313: Hispanic | AB313: Married | AC313: Fully Meets | AD313: 3 | AE313: =VLOOKUP(W313,Sheet4!$A$4:$B$53,2,FALSE) -> 0
A314: 1012 | B314: Skyler | C314: Blackwell | D314: 44144 | E314: 44353 | F314: 6 | G314: Attrition | H314: Software Engineer | I314: Candice Schmidt | J314: skyler.blackwell@bilearner.com | K314: TNS | L314: Voluntarily Terminated | M314: Contract | N314: Zone A | O314: Temporary | P314: Involuntary | Q314: Get apply economy artist right benefit ground. | R314: Software Engineering | S314: General - Eng | T314: 28766 | U314: 47.213889 | V314: 40-49 | W314: MA | X314: Administrative | Y314: Male | Z314: 67544 | AA314: White | AB314: Single | AC314: Fully Meets | AD314: 3 | AE314: =VLOOKUP(W314,Sheet4!$A$4:$B$53,2,FALSE) -> 0
A315: 1014 | B315: Kole | C315: Quinn | D315: 44926 | E315: 45120 | F315: 6 | G315: Attrition | H315: Shared Services Manager | I315: Jermaine Weaver | J315: kole.quinn@bilearner.com | K315: WBL | L315: Active | M315: Part-Time | N315: Zone A | O315: Full-Time | P315: Retirement | Q315: I back place no three offer economic. | R315: Software Engineering | S315: Catv | T315: 19553 | U315: 72.436111 | V315: 70-79 | W315: MA | X315: Clerk | Y315: Male | Z315: 2562 | AA315: Other | AB315: Single | AC315: Fully Meets | AD315: 3 | AE315: =VLOOKUP(W315,Sheet4!$A$4:$B$53,2,FALSE) -> 0
A316: 1016 | B316: Jayda | C316: Reese | D316: 43882 | E316: 44345 | F316: 15 | G316: Attrition | H316: Senior BI Developer | I316: Tyler Davis | J316: jayda.reese@bilearner.com | K316: PL | L316: Active | M316: Part-Time | N316: Zone B | O316: Part-Time | P316: Involuntary | Q316: Friend agree stock teach price fish. | R316: Admin Offices | S316: Shop (Fleet) | T316: 20522 | U316: 69.783333 | V316: 60-69 | W316: MA | X316: Mechanic | Y316: Female | Z316: 64065 | AA316: White | AB316: Single | AC316: Fully Meets | AD316: 3 | AE316: =VLOOKUP(W316,Sheet4!$A$4:$B$53,2,FALSE) -> 0
A317: 1017 | B317: Julien | C317: Whitehead | D317: 44081 | E317: 44545 | F317: 15 | G317: Attrition | H317: Senior BI Developer | I317: Joshua Gonzalez | J317: julien.whitehead@bilearner.com | K317: BPC | L317: Active | M317: Full-Time | N317: Zone B | O317: Full-Time | P317: Involuntary | Q317: True system strong often experience. | R317: Admin Offices | S317: Field Operations | T317: 17353 | U317: 78.458333 | V317: 70-79 | W317: MA | X317: Laborer | Y317: Female | Z317: 97374 | AA317: Black | AB317: Single | AC317: Fully Meets | AD317: 3 | AE317: =VLOOKUP(W317,Sheet4!$A$4:$B$53,2,FALSE) -> 0
A318: 1018 | B318: Alan | C318: Haynes | D318: 44001 | E318: 44538 | F318: 17 | G318: Attrition | H318: Senior BI Developer | I318: Justin Sherman | J318: alan.haynes@bilearner.com | K318: CCDR | L318: Active | M318: Part-Time | N318: Zone A | O318: Part-Time | P318: Involuntary | Q318: When price group admit fall fly around. | R318: Admin Offices | S318: General - Con | T318: 15396 | U318: 83.822222 | V318: 80-89 | W318: MA | X318: Laborer | Y318: Female | Z318: 87646 | AA318: White | AB318: Married | AC318: Fully Meets | AD318: 3 | AE318: =VLOOKUP(W318,Sheet4!$A$4:$B$53,2,FALSE) -> 0
A319: 1019 | B319: Kamryn | C319: Herrera | D319: 44848 | E319: 45135 | F319: 9 | G319: Attrition | H319: Software Engineer | I319: Sara Holland | J319: kamryn.herrera@bilearner.com | K319: EW | L319: Voluntarily Terminated | M319: Full-Time | N319: Zone A | O319: Temporary | P319: Retirement | Q319: Article tough away forward home. Night author so. | R319: Software Engineering | S319: Fielders | T319: 28822 | U319: 47.061111 | V319: 40-49 | W319: MA | X319: Engineer | Y319: Male | Z319: 77974 | AA319: Hispanic | AB319: Widowed | AC319: Fully Meets | AD319: 3 | AE319: =VLOOKUP(W319,Sheet4!$A$4:$B$53,2,FALSE) -> 0
A320: 1020 | B320: Kelvin | C320: Foster | D320: 45097 | E320: 45125 | F320: 0 | G320: Attrition | H320: Software Engineer | I320: Shelia Graham | J320: kelvin.foster@bilearner.com | K320: MSC | L320: Voluntarily Terminated | M320: Contract | N320: Zone C | O320: Full-Time | P320: Resignation | Q320: Man issue never strategy will maintain resource. | R320: Software Engineering | S320: Field Operations | T320: 33227 | U320: 35 | V320: 30-39 | W320: MA | X320: Supervisor | Y320: Female | Z320: 42126 | AA320: Black | AB320: Widowed | AC320: Fully Meets | AD320: 3 | AE320: =VLOOKUP(W320,Sheet4!$A$4:$B$53,2,FALSE) -> 0
A321: 1021 | B321: Joe | C321: Fletcher | D321: 44144 | E321: 45124 | F321: 32 | G321: Attrition | H321: Software Engineer | I321: Amanda Hayden | J321: joe.fletcher@bilearner.com | K321: TNS | L321: Voluntarily Terminated | M321: Full-Time | N321: Zone C | O321: Full-Time | P321: Resignation | Q321: Section hospital clearly season history. | R321: Software Engineering | S321: General - Eng | T321: 32533 | U321: 36.902778 | V321: 30-39 | W321: MA | X321: Billing | Y321: Male | Z321: 51613 | AA321: Hispanic | AB321: Single | AC321: Fully Meets | AD321: 3 | AE321: =VLOOKUP(W321,Sheet4!$A$4:$B$53,2,FALSE) -> 0
... A1536: 3425 | B1536: Kendra | C1536: Braun | D1536: 43613 | E1536: 44492 | F1536: 28 | G1536: Attrition | H1536: Production Technician I | I1536: Michael Woods | J1536: kendra.braun@bilearner.com | K1536: WBL | L1536: Voluntarily Terminated | M1536: Contract | N1536: Zone B | O1536: Full-Time | P1536: Resignation | Q1536: Fine expect election either turn. | R1536: Production | S1536: Aerial | T1536: 19872 | U1536: 71.561111 | V1536: 70-79 | W1536: MA | X1536: Foreman | Y1536: Female | Z1536: 3807 | AA1536: Hispanic | AB1536: Divorced | AC1536: Fully Meets | AD1536: 2 | AE1536: =VLOOKUP(W1536,Sheet4!$A$4:$B$53,2,FALSE) -> 0

Sheet Sheet4
A4: AL | E4: Alabama | F4: 4
A5: AK | E5: Arizona | F5: 14
A6: AZ | E6: California | F6: 6
A7: AR | E7: Colorado | F7: 11
A8: CA | E8: Connecticut | F8: 19
A9: CO | E9: Georgia | F9: 2
A10: CT | E10: Idaho | F10: 15
A11: DE | E11: Indiana | F11: 8
A12: FL | E12: Kentucky | F12: 12
A13: GA | E13: Maine | F13: 1
A14: HI | E14: Massachusetts | F14: 1362
A15: ID | E15: Montana | F15: 1
... A27: MS | E27: Washington | F27: 9
A28: MO
A29: MT
A30: NE
A31: NV
A32: NH
A33: NJ
A34: NM
A35: NY
A36: NC
A37: ND
A38: OH
A39: OK
... A53: WY
